{"v":"4.10.2","fr":24,"ip":0,"op":72,"w":151,"h":78,"nm":"Maharajah Jungle Tigers 3","ddd":0,"assets":[],"layers":[{"ddd":0,"ind":1,"ty":3,"nm":"Null 12","sr":1,"ks":{"o":{"a":0,"k":0,"ix":11},"r":{"a":0,"k":0,"ix":10},"p":{"a":0,"k":[75.5,39,0],"ix":2},"a":{"a":0,"k":[0,0,0],"ix":1},"s":{"a":0,"k":[33.3,33.3,100],"ix":6}},"ao":0,"ip":0,"op":240,"st":0,"bm":0},{"ddd":0,"ind":2,"ty":4,"nm":"tiger 1 head 2","parent":1,"sr":1,"ks":{"o":{"a":0,"k":100,"ix":11},"r":{"a":1,"k":[{"i":{"x":[0.338],"y":[1]},"o":{"x":[0.84],"y":[0]},"n":["0p338_1_0p84_0"],"t":6,"s":[0],"e":[22]},{"i":{"x":[0.667],"y":[1]},"o":{"x":[0.333],"y":[0]},"n":["0p667_1_0p333_0"],"t":18,"s":[22],"e":[22]},{"i":{"x":[0.351],"y":[1]},"o":{"x":[0.808],"y":[0]},"n":["0p351_1_0p808_0"],"t":35,"s":[22],"e":[0]},{"t":47}],"ix":10},"p":{"a":0,"k":[-41.726,64.014,0],"ix":2},"a":{"a":0,"k":[71.507,44.618,0],"ix":1},"s":{"a":0,"k":[-100,100,100],"ix":6}},"ao":0,"shapes":[{"ty":"gr","it":[{"ty":"rc","d":1,"s":{"a":1,"k":[{"i":{"x":[0.667,0.667],"y":[1,1]},"o":{"x":[0.333,0.333],"y":[0,0]},"n":["0p667_1_0p333_0","0p667_1_0p333_0"],"t":0,"s":[27,27],"e":[27,8]},{"i":{"x":[0.667,0.667],"y":[1,1]},"o":{"x":[0.333,0.333],"y":[0,0]},"n":["0p667_1_0p333_0","0p667_1_0p333_0"],"t":1,"s":[27,8],"e":[27,27]},{"i":{"x":[0.667,0.667],"y":[1,1]},"o":{"x":[0.333,0.333],"y":[0,0]},"n":["0p667_1_0p333_0","0p667_1_0p333_0"],"t":4,"s":[27,27],"e":[27,27]},{"i":{"x":[0.667,0.667],"y":[1,1]},"o":{"x":[0.333,0.333],"y":[0,0]},"n":["0p667_1_0p333_0","0p667_1_0p333_0"],"t":20,"s":[27,27],"e":[27,8]},{"i":{"x":[0.667,0.667],"y":[1,1]},"o":{"x":[0.333,0.333],"y":[0,0]},"n":["0p667_1_0p333_0","0p667_1_0p333_0"],"t":21,"s":[27,8],"e":[27,27]},{"t":24}],"ix":2},"p":{"a":0,"k":[0,0],"ix":3},"r":{"a":0,"k":38,"ix":4},"nm":"Rectangle Path 1","mn":"ADBE Vector Shape - Rect","hd":false},{"ty":"fl","c":{"a":0,"k":[0.301960784314,0.262745098039,0.372549019608,1],"ix":4},"o":{"a":0,"k":100,"ix":5},"r":1,"nm":"Fill 1","mn":"ADBE Vector Graphic - Fill","hd":false},{"ty":"tr","p":{"a":0,"k":[83.121,35.002],"ix":2},"a":{"a":0,"k":[0,0],"ix":1},"s":{"a":0,"k":[38.07,38.07],"ix":3},"r":{"a":0,"k":0,"ix":6},"o":{"a":0,"k":100,"ix":7},"sk":{"a":0,"k":0,"ix":4},"sa":{"a":0,"k":0,"ix":5},"nm":"Transform"}],"nm":"eye 2","np":2,"cix":2,"ix":1,"mn":"ADBE Vector Group","hd":false},{"ty":"gr","it":[{"ty":"rc","d":1,"s":{"a":1,"k":[{"i":{"x":[0.667,0.667],"y":[1,1]},"o":{"x":[0.333,0.333],"y":[0,0]},"n":["0p667_1_0p333_0","0p667_1_0p333_0"],"t":0,"s":[27,27],"e":[27,8]},{"i":{"x":[0.667,0.667],"y":[1,1]},"o":{"x":[0.333,0.333],"y":[0,0]},"n":["0p667_1_0p333_0","0p667_1_0p333_0"],"t":1,"s":[27,8],"e":[27,27]},{"i":{"x":[0.667,0.667],"y":[1,1]},"o":{"x":[0.333,0.333],"y":[0,0]},"n":["0p667_1_0p333_0","0p667_1_0p333_0"],"t":4,"s":[27,27],"e":[27,27]},{"i":{"x":[0.667,0.667],"y":[1,1]},"o":{"x":[0.333,0.333],"y":[0,0]},"n":["0p667_1_0p333_0","0p667_1_0p333_0"],"t":20,"s":[27,27],"e":[27,8]},{"i":{"x":[0.667,0.667],"y":[1,1]},"o":{"x":[0.333,0.333],"y":[0,0]},"n":["0p667_1_0p333_0","0p667_1_0p333_0"],"t":21,"s":[27,8],"e":[27,27]},{"t":24}],"ix":2},"p":{"a":0,"k":[0,0],"ix":3},"r":{"a":0,"k":38,"ix":4},"nm":"Rectangle Path 1","mn":"ADBE Vector Shape - Rect","hd":false},{"ty":"fl","c":{"a":0,"k":[0.301960784314,0.262745098039,0.372549019608,1],"ix":4},"o":{"a":0,"k":100,"ix":5},"r":1,"nm":"Fill 1","mn":"ADBE Vector Graphic - Fill","hd":false},{"ty":"tr","p":{"a":0,"k":[60.621,35.002],"ix":2},"a":{"a":0,"k":[0,0],"ix":1},"s":{"a":0,"k":[38.07,38.07],"ix":3},"r":{"a":0,"k":0,"ix":6},"o":{"a":0,"k":100,"ix":7},"sk":{"a":0,"k":0,"ix":4},"sa":{"a":0,"k":0,"ix":5},"nm":"Transform"}],"nm":"eye 1","np":2,"cix":2,"ix":2,"mn":"ADBE Vector Group","hd":false},{"ty":"gr","it":[{"ind":0,"ty":"sh","ix":1,"ks":{"a":0,"k":{"i":[[0,0],[-1.937,-1.941],[-2.492,1.33]],"o":[[2.493,1.33],[1.935,-1.939],[0,0]],"v":[[-6.737,-2.462],[0.002,2.462],[6.737,-2.458]],"c":false},"ix":2},"nm":"Path 1","mn":"ADBE Vector Shape - Group","hd":false},{"ty":"st","c":{"a":0,"k":[0.301999978458,0.263000009574,0.372999991623,1],"ix":3},"o":{"a":0,"k":100,"ix":4},"w":{"a":0,"k":4.421,"ix":5},"lc":2,"lj":2,"nm":"Stroke 1","mn":"ADBE Vector Graphic - Stroke","hd":false},{"ty":"tr","p":{"a":0,"k":[71.856,13.514],"ix":2},"a":{"a":0,"k":[0,0],"ix":1},"s":{"a":0,"k":[100,100],"ix":3},"r":{"a":0,"k":0,"ix":6},"o":{"a":0,"k":100,"ix":7},"sk":{"a":0,"k":0,"ix":4},"sa":{"a":0,"k":0,"ix":5},"nm":"Transform"}],"nm":"Group 10","np":2,"cix":2,"ix":3,"mn":"ADBE Vector Group","hd":false},{"ty":"gr","it":[{"ind":0,"ty":"sh","ix":1,"ks":{"a":0,"k":{"i":[[0,0],[-3.92,-3.929],[-5.399,1.282]],"o":[[5.4,1.282],[3.92,-3.929],[0,0]],"v":[[-14.771,-3.979],[0,3.979],[14.771,-3.979]],"c":false},"ix":2},"nm":"Path 1","mn":"ADBE Vector Shape - Group","hd":false},{"ty":"st","c":{"a":0,"k":[0.301999978458,0.263000009574,0.372999991623,1],"ix":3},"o":{"a":0,"k":100,"ix":4},"w":{"a":0,"k":4.421,"ix":5},"lc":2,"lj":2,"nm":"Stroke 1","mn":"ADBE Vector Graphic - Stroke","hd":false},{"ty":"tr","p":{"a":0,"k":[71.858,22.615],"ix":2},"a":{"a":0,"k":[0,0],"ix":1},"s":{"a":0,"k":[100,100],"ix":3},"r":{"a":0,"k":0,"ix":6},"o":{"a":0,"k":100,"ix":7},"sk":{"a":0,"k":0,"ix":4},"sa":{"a":0,"k":0,"ix":5},"nm":"Transform"}],"nm":"Group 11","np":2,"cix":2,"ix":4,"mn":"ADBE Vector Group","hd":false},{"ty":"gr","it":[{"ind":0,"ty":"sh","ix":1,"ks":{"a":0,"k":{"i":[[0,0],[0,0],[0,0],[0,0],[0,0],[0,0]],"o":[[0,0],[0,0],[0,0],[0,0],[0,0],[0,0]],"v":[[0,-2.142],[0,-0.759],[4.199,2.142],[0,1.454],[-4.199,2.142],[0,-0.759]],"c":false},"ix":2},"nm":"Path 1","mn":"ADBE Vector Shape - Group","hd":false},{"ty":"st","c":{"a":0,"k":[0.301999978458,0.263000009574,0.372999991623,1],"ix":3},"o":{"a":0,"k":100,"ix":4},"w":{"a":0,"k":3.536,"ix":5},"lc":2,"lj":2,"nm":"Stroke 1","mn":"ADBE Vector Graphic - Stroke","hd":false},{"ty":"tr","p":{"a":0,"k":[71.858,56.193],"ix":2},"a":{"a":0,"k":[0,0],"ix":1},"s":{"a":0,"k":[100,100],"ix":3},"r":{"a":0,"k":0,"ix":6},"o":{"a":0,"k":100,"ix":7},"sk":{"a":0,"k":0,"ix":4},"sa":{"a":0,"k":0,"ix":5},"nm":"Transform"}],"nm":"Group 12","np":2,"cix":2,"ix":5,"mn":"ADBE Vector Group","hd":false},{"ty":"gr","it":[{"ind":0,"ty":"sh","ix":1,"ks":{"a":0,"k":{"i":[[0,0],[0,0],[0,0],[0,0],[0,0],[0,0]],"o":[[0,0],[0,0],[0,0],[0,0],[0,0],[0,0]],"v":[[0,-2.142],[0,-0.759],[4.199,2.142],[0,1.454],[-4.199,2.142],[0,-0.759]],"c":false},"ix":2},"nm":"Path 1","mn":"ADBE Vector Shape - Group","hd":false},{"ty":"fl","c":{"a":0,"k":[0.301999978458,0.263000009574,0.372999991623,1],"ix":4},"o":{"a":0,"k":100,"ix":5},"r":1,"nm":"Fill 1","mn":"ADBE Vector Graphic - Fill","hd":false},{"ty":"tr","p":{"a":0,"k":[71.858,56.193],"ix":2},"a":{"a":0,"k":[0,0],"ix":1},"s":{"a":0,"k":[100,100],"ix":3},"r":{"a":0,"k":0,"ix":6},"o":{"a":0,"k":100,"ix":7},"sk":{"a":0,"k":0,"ix":4},"sa":{"a":0,"k":0,"ix":5},"nm":"Transform"}],"nm":"Group 13","np":2,"cix":2,"ix":6,"mn":"ADBE Vector Group","hd":false},{"ty":"gr","it":[{"ind":0,"ty":"sh","ix":1,"ks":{"a":0,"k":{"i":[[0,0],[0,0],[0,0],[0,0],[0,0],[0,0]],"o":[[0,0],[0,0],[0,0],[0,0],[0,0],[0,0]],"v":[[0,4.284],[0,1.517],[8.399,-4.284],[0,-2.907],[-8.399,-4.284],[0,1.517]],"c":false},"ix":2},"nm":"Path 1","mn":"ADBE Vector Shape - Group","hd":false},{"ty":"fl","c":{"a":0,"k":[0.301999978458,0.263000009574,0.372999991623,1],"ix":4},"o":{"a":0,"k":100,"ix":5},"r":1,"nm":"Fill 1","mn":"ADBE Vector Graphic - Fill","hd":false},{"ty":"st","c":{"a":0,"k":[0.301999978458,0.263000009574,0.372999991623,1],"ix":3},"o":{"a":0,"k":100,"ix":4},"w":{"a":0,"k":3.536,"ix":5},"lc":2,"lj":2,"nm":"Stroke 1","mn":"ADBE Vector Graphic - Stroke","hd":false},{"ty":"tr","p":{"a":0,"k":[71.858,52.506],"ix":2},"a":{"a":0,"k":[0,0],"ix":1},"s":{"a":0,"k":[100,100],"ix":3},"r":{"a":0,"k":0,"ix":6},"o":{"a":0,"k":100,"ix":7},"sk":{"a":0,"k":0,"ix":4},"sa":{"a":0,"k":0,"ix":5},"nm":"Transform"}],"nm":"Group 15","np":3,"cix":2,"ix":7,"mn":"ADBE Vector Group","hd":false},{"ty":"gr","it":[{"ind":0,"ty":"sh","ix":1,"ks":{"a":0,"k":{"i":[[10.444,0],[5.028,8.336],[-3.241,5.47],[-4.179,-2.373],[0.766,-2.576],[-0.917,-1.949],[-1.339,-0.807],[-0.233,-0.39],[-0.044,-0.257],[-0.133,0.223],[-0.389,0.234],[0,0],[0.714,2.4],[-3.21,1.823],[-4.215,-7.113],[1.172,-6.547]],"o":[[-10.444,0],[-1.172,-6.547],[4.215,-7.113],[3.211,1.823],[-0.714,2.4],[0,0],[0.389,0.234],[0.134,0.223],[0.044,-0.257],[0.233,-0.39],[1.339,-0.807],[0.918,-1.949],[-0.766,-2.576],[4.18,-2.373],[3.241,5.47],[-5.028,8.336]],"v":[[0,21.818],[-24.612,7.908],[-21.75,-11.275],[-5.01,-19.445],[-4.719,-9.035],[-8.457,4.135],[-1.268,9.397],[-0.242,10.271],[0,11.005],[0.242,10.271],[1.268,9.397],[8.457,4.135],[4.72,-9.035],[5.01,-19.445],[21.75,-11.275],[24.612,7.908]],"c":true},"ix":2},"nm":"Path 1","mn":"ADBE Vector Shape - Group","hd":false},{"ty":"fl","c":{"a":0,"k":[0.925,0.902000038297,0.8,1],"ix":4},"o":{"a":0,"k":100,"ix":5},"r":1,"nm":"Fill 1","mn":"ADBE Vector Graphic - Fill","hd":false},{"ty":"tr","p":{"a":0,"k":[71.858,44.116],"ix":2},"a":{"a":0,"k":[0,0],"ix":1},"s":{"a":0,"k":[100,100],"ix":3},"r":{"a":0,"k":0,"ix":6},"o":{"a":0,"k":100,"ix":7},"sk":{"a":0,"k":0,"ix":4},"sa":{"a":0,"k":0,"ix":5},"nm":"Transform"}],"nm":"Group 18","np":2,"cix":2,"ix":8,"mn":"ADBE Vector Group","hd":false},{"ty":"gr","it":[{"ind":0,"ty":"sh","ix":1,"ks":{"a":0,"k":{"i":[[0,15.863],[-15.863,0],[0,-15.864],[15.864,0]],"o":[[0,-15.864],[15.864,0],[0,15.863],[-15.863,0]],"v":[[-28.723,0],[-0.001,-28.723],[28.723,0],[-0.001,28.723]],"c":true},"ix":2},"nm":"Path 1","mn":"ADBE Vector Shape - Group","hd":false},{"ty":"fl","c":{"a":0,"k":[0.961000031116,0.545000023935,0.277999997606,1],"ix":4},"o":{"a":0,"k":100,"ix":5},"r":1,"nm":"Fill 1","mn":"ADBE Vector Graphic - Fill","hd":false},{"ty":"tr","p":{"a":0,"k":[71.858,37.211],"ix":2},"a":{"a":0,"k":[0,0],"ix":1},"s":{"a":0,"k":[100,100],"ix":3},"r":{"a":0,"k":0,"ix":6},"o":{"a":0,"k":100,"ix":7},"sk":{"a":0,"k":0,"ix":4},"sa":{"a":0,"k":0,"ix":5},"nm":"Transform"}],"nm":"Group 19","np":2,"cix":2,"ix":9,"mn":"ADBE Vector Group","hd":false}],"ip":0,"op":240,"st":0,"bm":0},{"ddd":0,"ind":3,"ty":4,"nm":"tiger 1 ear 4","parent":2,"sr":1,"ks":{"o":{"a":0,"k":100,"ix":11},"r":{"a":1,"k":[{"i":{"x":[0.833],"y":[0.833]},"o":{"x":[0.167],"y":[0.167]},"n":["0p833_0p833_0p167_0p167"],"t":11,"s":[0],"e":[-21]},{"i":{"x":[0.833],"y":[0.833]},"o":{"x":[0.167],"y":[0.167]},"n":["0p833_0p833_0p167_0p167"],"t":13,"s":[-21],"e":[25]},{"i":{"x":[0.833],"y":[0.833]},"o":{"x":[0.167],"y":[0.167]},"n":["0p833_0p833_0p167_0p167"],"t":15,"s":[25],"e":[-13]},{"i":{"x":[0.833],"y":[0.833]},"o":{"x":[0.167],"y":[0.167]},"n":["0p833_0p833_0p167_0p167"],"t":17,"s":[-13],"e":[0]},{"t":19}],"ix":10},"p":{"a":0,"k":[53.507,20.118,0],"ix":2},"a":{"a":0,"k":[53.507,20.118,0],"ix":1},"s":{"a":0,"k":[100,100,100],"ix":6}},"ao":0,"shapes":[{"ty":"gr","it":[{"ind":0,"ty":"sh","ix":1,"ks":{"a":0,"k":{"i":[[0.18,-0.051],[0.086,-0.34],[0.199,-1.643],[-0.033,-0.067],[-3.416,-0.718],[0,0],[4.075,1.585]],"o":[[-0.313,0.088],[-0.402,1.598],[0.031,0.067],[1.551,3.126],[0,0],[-3.5,-2.77],[-0.174,-0.067]],"v":[[-5.286,-6.019],[-5.823,-5.199],[-6.691,-0.328],[-6.604,-0.124],[1.397,6.07],[6.691,0.649],[-4.744,-5.934]],"c":true},"ix":2},"nm":"Path 1","mn":"ADBE Vector Shape - Group","hd":false},{"ty":"fl","c":{"a":0,"k":[0.301999978458,0.263000009574,0.372999991623,1],"ix":4},"o":{"a":0,"k":100,"ix":5},"r":1,"nm":"Fill 1","mn":"ADBE Vector Graphic - Fill","hd":false},{"ty":"tr","p":{"a":0,"k":[49.323,17.055],"ix":2},"a":{"a":0,"k":[0,0],"ix":1},"s":{"a":0,"k":[100,100],"ix":3},"r":{"a":0,"k":0,"ix":6},"o":{"a":0,"k":100,"ix":7},"sk":{"a":0,"k":0,"ix":4},"sa":{"a":0,"k":0,"ix":5},"nm":"Transform"}],"nm":"Group 26","np":2,"cix":2,"ix":1,"mn":"ADBE Vector Group","hd":false},{"ty":"gr","it":[{"ind":0,"ty":"sh","ix":1,"ks":{"a":0,"k":{"i":[[0,0],[2.244,1.58],[2.637,0.759],[0.755,-0.57],[0.189,-0.399],[-1.551,-3.127],[-3.415,-0.718]],"o":[[-0.407,-2.714],[-2.244,-1.58],[-0.909,-0.261],[-0.352,0.265],[-1.494,3.154],[1.551,3.127],[0,0]],"v":[[8.494,1.396],[4.017,-5.246],[-3.507,-8.491],[-6.236,-8.403],[-7,-7.338],[-6.909,2.78],[1.093,8.973]],"c":false},"ix":2},"nm":"Path 1","mn":"ADBE Vector Shape - Group","hd":false},{"ty":"fl","c":{"a":0,"k":[0.961000031116,0.545000023935,0.277999997606,1],"ix":4},"o":{"a":0,"k":100,"ix":5},"r":1,"nm":"Fill 1","mn":"ADBE Vector Graphic - Fill","hd":false},{"ty":"tr","p":{"a":0,"k":[49.627,14.151],"ix":2},"a":{"a":0,"k":[0,0],"ix":1},"s":{"a":0,"k":[100,100],"ix":3},"r":{"a":0,"k":0,"ix":6},"o":{"a":0,"k":100,"ix":7},"sk":{"a":0,"k":0,"ix":4},"sa":{"a":0,"k":0,"ix":5},"nm":"Transform"}],"nm":"Group 27","np":2,"cix":2,"ix":2,"mn":"ADBE Vector Group","hd":false}],"ip":0,"op":240,"st":0,"bm":0},{"ddd":0,"ind":4,"ty":4,"nm":"tiger 1 ear 3","parent":2,"sr":1,"ks":{"o":{"a":0,"k":100,"ix":11},"r":{"a":1,"k":[{"i":{"x":[0.833],"y":[0.833]},"o":{"x":[0.167],"y":[0.167]},"n":["0p833_0p833_0p167_0p167"],"t":14,"s":[0],"e":[-26]},{"i":{"x":[0.833],"y":[0.833]},"o":{"x":[0.167],"y":[0.167]},"n":["0p833_0p833_0p167_0p167"],"t":16,"s":[-26],"e":[19]},{"i":{"x":[0.833],"y":[0.833]},"o":{"x":[0.167],"y":[0.167]},"n":["0p833_0p833_0p167_0p167"],"t":18,"s":[19],"e":[-10]},{"i":{"x":[0.833],"y":[0.833]},"o":{"x":[0.167],"y":[0.167]},"n":["0p833_0p833_0p167_0p167"],"t":20,"s":[-10],"e":[0]},{"t":23}],"ix":10},"p":{"a":0,"k":[89.507,20.118,0],"ix":2},"a":{"a":0,"k":[89.507,20.118,0],"ix":1},"s":{"a":0,"k":[100,100,100],"ix":6}},"ao":0,"shapes":[{"ty":"gr","it":[{"ind":0,"ty":"sh","ix":1,"ks":{"a":0,"k":{"i":[[-0.18,-0.051],[-0.086,-0.34],[-0.199,-1.643],[0.033,-0.067],[3.416,-0.718],[0,0],[-4.074,1.585]],"o":[[0.312,0.088],[0.402,1.598],[-0.031,0.067],[-1.551,3.126],[0,0],[3.5,-2.77],[0.175,-0.067]],"v":[[5.287,-6.019],[5.823,-5.199],[6.691,-0.328],[6.604,-0.124],[-1.397,6.07],[-6.691,0.649],[4.743,-5.934]],"c":true},"ix":2},"nm":"Path 1","mn":"ADBE Vector Shape - Group","hd":false},{"ty":"fl","c":{"a":0,"k":[0.301999978458,0.263000009574,0.372999991623,1],"ix":4},"o":{"a":0,"k":100,"ix":5},"r":1,"nm":"Fill 1","mn":"ADBE Vector Graphic - Fill","hd":false},{"ty":"tr","p":{"a":0,"k":[94.393,17.055],"ix":2},"a":{"a":0,"k":[0,0],"ix":1},"s":{"a":0,"k":[100,100],"ix":3},"r":{"a":0,"k":0,"ix":6},"o":{"a":0,"k":100,"ix":7},"sk":{"a":0,"k":0,"ix":4},"sa":{"a":0,"k":0,"ix":5},"nm":"Transform"}],"nm":"Group 24","np":2,"cix":2,"ix":1,"mn":"ADBE Vector Group","hd":false},{"ty":"gr","it":[{"ind":0,"ty":"sh","ix":1,"ks":{"a":0,"k":{"i":[[0,0],[-2.244,1.58],[-2.637,0.759],[-0.754,-0.57],[-0.189,-0.399],[1.552,-3.127],[3.415,-0.718]],"o":[[0.407,-2.714],[2.244,-1.58],[0.909,-0.261],[0.353,0.265],[1.494,3.154],[-1.55,3.127],[0,0]],"v":[[-8.494,1.396],[-4.017,-5.246],[3.507,-8.491],[6.235,-8.403],[7,-7.338],[6.908,2.78],[-1.093,8.973]],"c":false},"ix":2},"nm":"Path 1","mn":"ADBE Vector Shape - Group","hd":false},{"ty":"fl","c":{"a":0,"k":[0.961000031116,0.545000023935,0.277999997606,1],"ix":4},"o":{"a":0,"k":100,"ix":5},"r":1,"nm":"Fill 1","mn":"ADBE Vector Graphic - Fill","hd":false},{"ty":"tr","p":{"a":0,"k":[94.089,14.151],"ix":2},"a":{"a":0,"k":[0,0],"ix":1},"s":{"a":0,"k":[100,100],"ix":3},"r":{"a":0,"k":0,"ix":6},"o":{"a":0,"k":100,"ix":7},"sk":{"a":0,"k":0,"ix":4},"sa":{"a":0,"k":0,"ix":5},"nm":"Transform"}],"nm":"Group 25","np":2,"cix":2,"ix":2,"mn":"ADBE Vector Group","hd":false}],"ip":0,"op":240,"st":0,"bm":0},{"ddd":0,"ind":5,"ty":4,"nm":"tiger 2","parent":1,"sr":1,"ks":{"o":{"a":0,"k":100,"ix":11},"r":{"a":0,"k":0,"ix":10},"p":{"a":0,"k":[-102.726,81.014,0],"ix":2},"a":{"a":0,"k":[132.507,61.618,0],"ix":1},"s":{"a":0,"k":[-100,100,100],"ix":6}},"ao":0,"shapes":[{"ty":"gr","it":[{"ind":0,"ty":"sh","ix":1,"ks":{"a":0,"k":{"i":[[4.05,-4.669],[0.866,0],[0.585,0.507],[-1.12,1.292],[-0.291,6.951],[-0.828,0.525],[-0.868,-3.093]],"o":[[-0.611,0.706],[-0.719,0],[-1.292,-1.12],[4.369,-5.036],[0.044,-1.054],[1.8,2.548],[-1.229,6.194]],"v":[[-1.123,12.03],[-3.462,13.098],[-5.487,12.34],[-5.798,7.975],[1.428,-10.616],[2.879,-13.098],[6.918,-4.597]],"c":true},"ix":2},"nm":"Path 1","mn":"ADBE Vector Shape - Group","hd":false},{"ty":"fl","c":{"a":0,"k":[0.301999978458,0.263000009574,0.372999991623,1],"ix":4},"o":{"a":0,"k":100,"ix":5},"r":1,"nm":"Fill 1","mn":"ADBE Vector Graphic - Fill","hd":false},{"ty":"tr","p":{"a":0,"k":[191.755,52.549],"ix":2},"a":{"a":0,"k":[0,0],"ix":1},"s":{"a":0,"k":[100,100],"ix":3},"r":{"a":0,"k":0,"ix":6},"o":{"a":0,"k":100,"ix":7},"sk":{"a":0,"k":0,"ix":4},"sa":{"a":0,"k":0,"ix":5},"nm":"Transform"}],"nm":"Group 1","np":2,"cix":2,"ix":1,"mn":"ADBE Vector Group","hd":false},{"ty":"gr","it":[{"ind":0,"ty":"sh","ix":1,"ks":{"a":0,"k":{"i":[[1.244,0],[0.365,0.141],[-0.612,1.595],[0.063,5.915],[0.846,2.273],[-0.148,0.588],[-2.067,-0.955],[-0.026,-2.388],[1.96,-5.102]],"o":[[-0.369,0],[-1.594,-0.613],[1.873,-4.873],[-0.026,-2.589],[-0.226,-0.611],[2.382,0.487],[0.589,2.25],[0.073,6.997],[-0.474,1.23]],"v":[[-1.794,15.019],[-2.905,14.813],[-4.683,10.815],[-0.968,-5.752],[-2.301,-13.183],[-2.397,-15.019],[4.284,-12.841],[5.222,-5.818],[1.095,13.034]],"c":true},"ix":2},"nm":"Path 1","mn":"ADBE Vector Shape - Group","hd":false},{"ty":"fl","c":{"a":0,"k":[0.301999978458,0.263000009574,0.372999991623,1],"ix":4},"o":{"a":0,"k":100,"ix":5},"r":1,"nm":"Fill 1","mn":"ADBE Vector Graphic - Fill","hd":false},{"ty":"tr","p":{"a":0,"k":[179.411,43.241],"ix":2},"a":{"a":0,"k":[0,0],"ix":1},"s":{"a":0,"k":[100,100],"ix":3},"r":{"a":0,"k":0,"ix":6},"o":{"a":0,"k":100,"ix":7},"sk":{"a":0,"k":0,"ix":4},"sa":{"a":0,"k":0,"ix":5},"nm":"Transform"}],"nm":"Group 2","np":2,"cix":2,"ix":2,"mn":"ADBE Vector Group","hd":false},{"ty":"gr","it":[{"ind":0,"ty":"sh","ix":1,"ks":{"a":0,"k":{"i":[[0.493,1.191],[-0.785,5.091],[-0.124,1.419],[4.858,4.406],[0.148,0.553],[-2.349,0.286],[0.715,-8.181],[0.272,-1.754],[-1.397,-3.374],[1.578,-0.654],[0.396,0]],"o":[[-2.061,-4.974],[0.255,-1.651],[0.63,-7.2],[-0.456,-0.413],[2.292,-0.498],[4.954,5.413],[-0.141,1.622],[-0.693,4.498],[0.654,1.578],[-0.388,0.16],[-1.213,0]],"v":[[-0.125,19.128],[-0.51,3.292],[0.11,-1.337],[-6.088,-18.348],[-6.99,-19.833],[-0.037,-21.04],[6.275,-0.798],[5.606,4.237],[5.592,16.761],[3.918,20.804],[2.734,21.04]],"c":true},"ix":2},"nm":"Path 1","mn":"ADBE Vector Shape - Group","hd":false},{"ty":"fl","c":{"a":0,"k":[0.301999978458,0.263000009574,0.372999991623,1],"ix":4},"o":{"a":0,"k":100,"ix":5},"r":1,"nm":"Fill 1","mn":"ADBE Vector Graphic - Fill","hd":false},{"ty":"tr","p":{"a":0,"k":[162.617,48.989],"ix":2},"a":{"a":0,"k":[0,0],"ix":1},"s":{"a":0,"k":[100,100],"ix":3},"r":{"a":0,"k":0,"ix":6},"o":{"a":0,"k":100,"ix":7},"sk":{"a":0,"k":0,"ix":4},"sa":{"a":0,"k":0,"ix":5},"nm":"Transform"}],"nm":"Group 3","np":2,"cix":2,"ix":3,"mn":"ADBE Vector Group","hd":false},{"ty":"gr","it":[{"ind":0,"ty":"sh","ix":1,"ks":{"a":0,"k":{"i":[[1.549,0],[0.123,0.014],[-0.198,1.697],[5.298,3.558],[0.231,0.483],[-2.31,0.663],[0.86,-7.364]],"o":[[-0.119,0],[-1.697,-0.198],[0.714,-6.113],[-0.477,-0.32],[2.312,-0.668],[5.664,5.033],[-0.184,1.576]],"v":[[3.934,11.438],[3.571,11.417],[0.857,7.985],[-6.808,-8.183],[-7.864,-9.42],[-0.935,-11.438],[7.004,8.702]],"c":true},"ix":2},"nm":"Path 1","mn":"ADBE Vector Shape - Group","hd":false},{"ty":"fl","c":{"a":0,"k":[0.301999978458,0.263000009574,0.372999991623,1],"ix":4},"o":{"a":0,"k":100,"ix":5},"r":1,"nm":"Fill 1","mn":"ADBE Vector Graphic - Fill","hd":false},{"ty":"tr","p":{"a":0,"k":[147.238,42.995],"ix":2},"a":{"a":0,"k":[0,0],"ix":1},"s":{"a":0,"k":[100,100],"ix":3},"r":{"a":0,"k":0,"ix":6},"o":{"a":0,"k":100,"ix":7},"sk":{"a":0,"k":0,"ix":4},"sa":{"a":0,"k":0,"ix":5},"nm":"Transform"}],"nm":"Group 4","np":2,"cix":2,"ix":4,"mn":"ADBE Vector Group","hd":false},{"ty":"gr","it":[{"ind":0,"ty":"sh","ix":1,"ks":{"a":0,"k":{"i":[[1.439,0],[0.21,0.042],[-0.343,1.675],[4.13,4.498],[0.128,0.266],[-2.207,0.554],[1.41,-6.887]],"o":[[-0.206,0],[-1.674,-0.343],[1.187,-5.801],[-0.209,-0.228],[2.254,-0.399],[4.275,5.751],[-0.3,1.465]],"v":[[1.93,11.302],[1.305,11.24],[-1.105,7.587],[-5.875,-9.11],[-6.368,-9.86],[0.319,-11.302],[4.958,8.829]],"c":true},"ix":2},"nm":"Path 1","mn":"ADBE Vector Shape - Group","hd":false},{"ty":"fl","c":{"a":0,"k":[0.301999978458,0.263000009574,0.372999991623,1],"ix":4},"o":{"a":0,"k":100,"ix":5},"r":1,"nm":"Fill 1","mn":"ADBE Vector Graphic - Fill","hd":false},{"ty":"tr","p":{"a":0,"k":[132.505,46.657],"ix":2},"a":{"a":0,"k":[0,0],"ix":1},"s":{"a":0,"k":[100,100],"ix":3},"r":{"a":0,"k":0,"ix":6},"o":{"a":0,"k":100,"ix":7},"sk":{"a":0,"k":0,"ix":4},"sa":{"a":0,"k":0,"ix":5},"nm":"Transform"}],"nm":"Group 5","np":2,"cix":2,"ix":5,"mn":"ADBE Vector Group","hd":false},{"ty":"gr","it":[{"ind":0,"ty":"sh","ix":1,"ks":{"a":0,"k":{"i":[[1.609,0],[0.074,0.005],[-0.121,1.705],[0.727,4.023],[0.989,1.685],[0.03,0.466],[-2.187,0.188],[-0.423,-2.336],[0.323,-4.564]],"o":[[-0.074,0],[-1.704,-0.12],[0.295,-4.183],[-0.395,-2.186],[-0.252,-0.429],[2.163,-0.002],[0.958,1.968],[0.865,4.786],[-0.115,1.63]],"v":[[0.999,11.705],[0.777,11.698],[-2.091,8.392],[-2.217,-4.139],[-4.332,-10.056],[-4.738,-11.418],[1.784,-11.705],[3.873,-5.24],[4.082,8.829]],"c":true},"ix":2},"nm":"Path 1","mn":"ADBE Vector Shape - Group","hd":false},{"ty":"fl","c":{"a":0,"k":[0.301999978458,0.263000009574,0.372999991623,1],"ix":4},"o":{"a":0,"k":100,"ix":5},"r":1,"nm":"Fill 1","mn":"ADBE Vector Graphic - Fill","hd":false},{"ty":"tr","p":{"a":0,"k":[117.52,49.391],"ix":2},"a":{"a":0,"k":[0,0],"ix":1},"s":{"a":0,"k":[100,100],"ix":3},"r":{"a":0,"k":0,"ix":6},"o":{"a":0,"k":100,"ix":7},"sk":{"a":0,"k":0,"ix":4},"sa":{"a":0,"k":0,"ix":5},"nm":"Transform"}],"nm":"Group 6","np":2,"cix":2,"ix":6,"mn":"ADBE Vector Group","hd":false},{"ty":"gr","it":[{"ind":0,"ty":"sh","ix":1,"ks":{"a":0,"k":{"i":[[1.022,0],[0.515,0.328],[-0.918,1.442],[2.114,6.077],[-0.128,0.551],[-2.07,-0.147],[4.219,-6.624]],"o":[[-0.569,0],[-1.442,-0.918],[3.342,-5.248],[-0.199,-0.573],[2.094,0.294],[2.352,7.68],[-0.59,0.927]],"v":[[-2.185,12.416],[-3.845,11.931],[-4.793,7.659],[-2.802,-10.702],[-2.885,-12.416],[3.359,-11.74],[0.427,10.983]],"c":true},"ix":2},"nm":"Path 1","mn":"ADBE Vector Shape - Group","hd":false},{"ty":"fl","c":{"a":0,"k":[0.301999978458,0.263000009574,0.372999991623,1],"ix":4},"o":{"a":0,"k":100,"ix":5},"r":1,"nm":"Fill 1","mn":"ADBE Vector Graphic - Fill","hd":false},{"ty":"tr","p":{"a":0,"k":[103.599,49.526],"ix":2},"a":{"a":0,"k":[0,0],"ix":1},"s":{"a":0,"k":[100,100],"ix":3},"r":{"a":0,"k":0,"ix":6},"o":{"a":0,"k":100,"ix":7},"sk":{"a":0,"k":0,"ix":4},"sa":{"a":0,"k":0,"ix":5},"nm":"Transform"}],"nm":"Group 7","np":2,"cix":2,"ix":7,"mn":"ADBE Vector Group","hd":false},{"ty":"gr","it":[{"ind":0,"ty":"sh","ix":1,"ks":{"a":0,"k":{"i":[[0,0],[0,13.518]],"o":[[13.396,0],[0,0]],"v":[[-11.308,11.421],[11.308,-11.421]],"c":false},"ix":2},"nm":"Path 1","mn":"ADBE Vector Shape - Group","hd":false},{"ty":"st","c":{"a":0,"k":[0.961000031116,0.545000023935,0.277999997606,1],"ix":3},"o":{"a":0,"k":100,"ix":4},"w":{"a":0,"k":13.262,"ix":5},"lc":2,"lj":2,"nm":"Stroke 1","mn":"ADBE Vector Graphic - Stroke","hd":false},{"ty":"tr","p":{"a":0,"k":[105.199,73.656],"ix":2},"a":{"a":0,"k":[0,0],"ix":1},"s":{"a":0,"k":[100,100],"ix":3},"r":{"a":0,"k":0,"ix":6},"o":{"a":0,"k":100,"ix":7},"sk":{"a":0,"k":0,"ix":4},"sa":{"a":0,"k":0,"ix":5},"nm":"Transform"}],"nm":"Group 8","np":2,"cix":2,"ix":8,"mn":"ADBE Vector Group","hd":false},{"ty":"gr","it":[{"ind":0,"ty":"sh","ix":1,"ks":{"a":0,"k":{"i":[[0,0],[9.284,-3.101],[11.076,0.472],[9.512,-5.694]],"o":[[0.75,9.541],[-10.515,3.513],[-11.076,-0.471],[0,0]],"v":[[39.837,-16.031],[24.708,8.506],[-8.284,10.516],[-40.587,16.031]],"c":false},"ix":2},"nm":"Path 1","mn":"ADBE Vector Shape - Group","hd":false},{"ty":"st","c":{"a":0,"k":[0.961000031116,0.545000023935,0.277999997606,1],"ix":3},"o":{"a":0,"k":100,"ix":4},"w":{"a":0,"k":13.262,"ix":5},"lc":2,"lj":2,"nm":"Stroke 1","mn":"ADBE Vector Graphic - Stroke","hd":false},{"ty":"tr","p":{"a":0,"k":[87.899,74.051],"ix":2},"a":{"a":0,"k":[0,0],"ix":1},"s":{"a":0,"k":[100,100],"ix":3},"r":{"a":0,"k":0,"ix":6},"o":{"a":0,"k":100,"ix":7},"sk":{"a":0,"k":0,"ix":4},"sa":{"a":0,"k":0,"ix":5},"nm":"Transform"}],"nm":"Group 9","np":2,"cix":2,"ix":9,"mn":"ADBE Vector Group","hd":false},{"ty":"gr","it":[{"ind":0,"ty":"sh","ix":1,"ks":{"a":0,"k":{"i":[[0,0],[-2.578,-6.679],[-5.277,-4.837],[8.129,-0.295],[2.258,-5.751],[-0.241,-0.745],[-1.41,-0.289],[-18.865,0],[7.248,12.048]],"o":[[-6.074,3.788],[2.577,6.679],[-7.539,-3.057],[-6.175,0.223],[-0.287,0.73],[0.444,1.369],[10.605,2.173],[12.23,0],[0,0]],"v":[[-4.864,-23.11],[-9.629,-3.893],[3.676,12.707],[-20.18,8.501],[-35.741,16.465],[-35.979,18.757],[-32.496,20.937],[16.902,22.466],[28.972,-2.627]],"c":false},"ix":2},"nm":"Path 1","mn":"ADBE Vector Shape - Group","hd":false},{"ty":"fl","c":{"a":0,"k":[0.961000031116,0.545000023935,0.277999997606,1],"ix":4},"o":{"a":0,"k":100,"ix":5},"r":1,"nm":"Fill 1","mn":"ADBE Vector Graphic - Fill","hd":false},{"ty":"tr","p":{"a":0,"k":[163.556,74.071],"ix":2},"a":{"a":0,"k":[0,0],"ix":1},"s":{"a":0,"k":[100,100],"ix":3},"r":{"a":0,"k":0,"ix":6},"o":{"a":0,"k":100,"ix":7},"sk":{"a":0,"k":0,"ix":4},"sa":{"a":0,"k":0,"ix":5},"nm":"Transform"}],"nm":"Group 20","np":2,"cix":2,"ix":10,"mn":"ADBE Vector Group","hd":false},{"ty":"gr","it":[{"ind":0,"ty":"sh","ix":1,"ks":{"a":0,"k":{"i":[[-4.364,0],[-4.328,2.131],[-7.044,0.097],[-10.368,3.228],[-6.301,-19.195],[9.109,0],[0,0],[7.058,11.208]],"o":[[5.15,0],[7.027,2.911],[10.931,-0.15],[16.725,-5.207],[-6.804,5.013],[0,0],[-12.829,0],[3.803,1.559]],"v":[[-52.128,0.203],[-37.782,-3.128],[-15.469,0.783],[14.779,-8.647],[64.454,7.374],[39.526,13.854],[-31.26,13.854],[-64.454,-2.221]],"c":true},"ix":2},"nm":"Path 1","mn":"ADBE Vector Shape - Group","hd":false},{"ty":"fl","c":{"a":0,"k":[0.925,0.902000038297,0.8,1],"ix":4},"o":{"a":0,"k":100,"ix":5},"r":1,"nm":"Fill 1","mn":"ADBE Vector Graphic - Fill","hd":false},{"ty":"tr","p":{"a":0,"k":[123.986,73.345],"ix":2},"a":{"a":0,"k":[0,0],"ix":1},"s":{"a":0,"k":[100,100],"ix":3},"r":{"a":0,"k":0,"ix":6},"o":{"a":0,"k":100,"ix":7},"sk":{"a":0,"k":0,"ix":4},"sa":{"a":0,"k":0,"ix":5},"nm":"Transform"}],"nm":"Group 22","np":2,"cix":2,"ix":11,"mn":"ADBE Vector Group","hd":false},{"ty":"gr","it":[{"ind":0,"ty":"sh","ix":1,"ks":{"a":0,"k":{"i":[[-9.871,1.582],[-16.555,-0.689],[7.177,-20.474],[14.46,0],[0,0],[6.943,11.684],[-11.105,6.785],[-5.383,-0.364],[-5.304,-0.992]],"o":[[15.798,-2.532],[21.067,0.876],[-5.511,15.716],[0,0],[-13.081,0],[-6.02,-10.132],[4.605,-2.812],[5.383,0.365],[9.85,1.842]],"v":[[-4.041,-20.025],[42.596,-29.476],[68.725,10.758],[34.523,30.165],[-36.263,30.165],[-69.882,13.438],[-64.609,-20.253],[-48.993,-23.396],[-33.045,-20.694]],"c":true},"ix":2},"nm":"Path 1","mn":"ADBE Vector Shape - Group","hd":false},{"ty":"fl","c":{"a":0,"k":[0.961000031116,0.545000023935,0.277999997606,1],"ix":4},"o":{"a":0,"k":100,"ix":5},"r":1,"nm":"Fill 1","mn":"ADBE Vector Graphic - Fill","hd":false},{"ty":"tr","p":{"a":0,"k":[128.988,57.035],"ix":2},"a":{"a":0,"k":[0,0],"ix":1},"s":{"a":0,"k":[100,100],"ix":3},"r":{"a":0,"k":0,"ix":6},"o":{"a":0,"k":100,"ix":7},"sk":{"a":0,"k":0,"ix":4},"sa":{"a":0,"k":0,"ix":5},"nm":"Transform"}],"nm":"Group 23","np":2,"cix":2,"ix":12,"mn":"ADBE Vector Group","hd":false},{"ty":"gr","it":[{"ind":0,"ty":"sh","ix":1,"ks":{"a":0,"k":{"i":[[0,0],[5.139,-1.718],[11.075,0.471],[9.512,-5.693]],"o":[[-0.906,5.341],[-10.514,3.512],[-11.077,-0.471],[0,0]],"v":[[38.31,-9.022],[26.985,1.498],[-6.006,3.509],[-38.31,9.022]],"c":false},"ix":2},"nm":"Path 1","mn":"ADBE Vector Shape - Group","hd":false},{"ty":"st","c":{"a":0,"k":[0.961000031116,0.545000023935,0.277999997606,1],"ix":3},"o":{"a":0,"k":100,"ix":4},"w":{"a":0,"k":13.262,"ix":5},"lc":2,"lj":2,"nm":"Stroke 1","mn":"ADBE Vector Graphic - Stroke","hd":false},{"ty":"tr","p":{"a":0,"k":[71.464,72.211],"ix":2},"a":{"a":0,"k":[0,0],"ix":1},"s":{"a":0,"k":[100,100],"ix":3},"r":{"a":0,"k":0,"ix":6},"o":{"a":0,"k":100,"ix":7},"sk":{"a":0,"k":0,"ix":4},"sa":{"a":0,"k":0,"ix":5},"nm":"Transform"}],"nm":"Group 28","np":2,"cix":2,"ix":13,"mn":"ADBE Vector Group","hd":false}],"ip":0,"op":240,"st":0,"bm":0},{"ddd":0,"ind":6,"ty":4,"nm":"tiger tail 2","parent":5,"sr":1,"ks":{"o":{"a":0,"k":100,"ix":11},"r":{"a":1,"k":[{"i":{"x":[0.667],"y":[1]},"o":{"x":[0.333],"y":[0]},"n":["0p667_1_0p333_0"],"t":0,"s":[36],"e":[4]},{"i":{"x":[0.667],"y":[1]},"o":{"x":[0.333],"y":[0]},"n":["0p667_1_0p333_0"],"t":15,"s":[4],"e":[51]},{"i":{"x":[0.667],"y":[1]},"o":{"x":[0.333],"y":[0]},"n":["0p667_1_0p333_0"],"t":21,"s":[51],"e":[36]},{"i":{"x":[0.667],"y":[1]},"o":{"x":[0.333],"y":[0]},"n":["0p667_1_0p333_0"],"t":26,"s":[36],"e":[4]},{"i":{"x":[0.667],"y":[1]},"o":{"x":[0.333],"y":[0]},"n":["0p667_1_0p333_0"],"t":37,"s":[4],"e":[51]},{"i":{"x":[0.667],"y":[1]},"o":{"x":[0.333],"y":[0]},"n":["0p667_1_0p333_0"],"t":43,"s":[51],"e":[36]},{"t":51}],"ix":10},"p":{"a":0,"k":[192.345,45.905,0],"ix":2},"a":{"a":0,"k":[309.857,105.518,0],"ix":1},"s":{"a":0,"k":[-113.859,100,100],"ix":6}},"ao":0,"shapes":[{"ty":"gr","it":[{"ind":0,"ty":"sh","ix":1,"ks":{"a":1,"k":[{"i":{"x":0.667,"y":1},"o":{"x":0.664,"y":0},"n":"0p667_1_0p664_0","t":0,"s":[{"i":[[0,0],[12.161,19.2]],"o":[[-4.596,-11.772],[0,0]],"v":[[19.675,15.44],[-30.198,1.176]],"c":false}],"e":[{"i":[[0,0],[15.802,7.359]],"o":[[-14.057,-11.784],[0,0]],"v":[[19.675,15.44],[-32.215,18.672]],"c":false}]},{"i":{"x":0.667,"y":1},"o":{"x":0.333,"y":0},"n":"0p667_1_0p333_0","t":4,"s":[{"i":[[0,0],[15.802,7.359]],"o":[[-14.057,-11.784],[0,0]],"v":[[19.675,15.44],[-32.215,18.672]],"c":false}],"e":[{"i":[[0,0],[12.848,-11.721]],"o":[[-12.68,-9.481],[0,0]],"v":[[19.675,15.44],[-31.357,20.283]],"c":false}]},{"i":{"x":0.667,"y":1},"o":{"x":0.333,"y":0},"n":"0p667_1_0p333_0","t":8,"s":[{"i":[[0,0],[12.848,-11.721]],"o":[[-12.68,-9.481],[0,0]],"v":[[19.675,15.44],[-31.357,20.283]],"c":false}],"e":[{"i":[[0,0],[18.711,-13.577]],"o":[[-11.303,-7.177],[0,0]],"v":[[19.675,15.44],[-30.744,15.498]],"c":false}]},{"i":{"x":0.667,"y":1},"o":{"x":0.333,"y":0},"n":"0p667_1_0p333_0","t":10,"s":[{"i":[[0,0],[18.711,-13.577]],"o":[[-11.303,-7.177],[0,0]],"v":[[19.675,15.44],[-30.744,15.498]],"c":false}],"e":[{"i":[[0,0],[25.345,-0.643]],"o":[[-7.667,-1.094],[0,0]],"v":[[19.675,15.44],[-27.011,-6.767]],"c":false}]},{"i":{"x":0.667,"y":1},"o":{"x":0.333,"y":0},"n":"0p667_1_0p333_0","t":14,"s":[{"i":[[0,0],[25.345,-0.643]],"o":[[-7.667,-1.094],[0,0]],"v":[[19.675,15.44],[-27.011,-6.767]],"c":false}],"e":[{"i":[[0,0],[10.379,15.746]],"o":[[-13.394,0.224],[0,0]],"v":[[19.675,15.44],[-21.986,-18.786]],"c":false}]},{"i":{"x":0.667,"y":1},"o":{"x":0.333,"y":0},"n":"0p667_1_0p333_0","t":16,"s":[{"i":[[0,0],[10.379,15.746]],"o":[[-13.394,0.224],[0,0]],"v":[[19.675,15.44],[-21.986,-18.786]],"c":false}],"e":[{"i":[[0,0],[4.116,22.688]],"o":[[-19.121,1.542],[0,0]],"v":[[19.675,15.44],[-22.085,-16.512]],"c":false}]},{"i":{"x":0.667,"y":1},"o":{"x":0.333,"y":0},"n":"0p667_1_0p333_0","t":18,"s":[{"i":[[0,0],[4.116,22.688]],"o":[[-19.121,1.542],[0,0]],"v":[[19.675,15.44],[-22.085,-16.512]],"c":false}],"e":[{"i":[[0,0],[15.802,7.359]],"o":[[-14.057,-11.784],[0,0]],"v":[[19.675,15.44],[-32.215,18.672]],"c":false}]},{"i":{"x":0.667,"y":1},"o":{"x":0.333,"y":0},"n":"0p667_1_0p333_0","t":26,"s":[{"i":[[0,0],[15.802,7.359]],"o":[[-14.057,-11.784],[0,0]],"v":[[19.675,15.44],[-32.215,18.672]],"c":false}],"e":[{"i":[[0,0],[12.848,-11.721]],"o":[[-12.68,-9.481],[0,0]],"v":[[19.675,15.44],[-31.357,20.283]],"c":false}]},{"i":{"x":0.667,"y":1},"o":{"x":0.333,"y":0},"n":"0p667_1_0p333_0","t":30,"s":[{"i":[[0,0],[12.848,-11.721]],"o":[[-12.68,-9.481],[0,0]],"v":[[19.675,15.44],[-31.357,20.283]],"c":false}],"e":[{"i":[[0,0],[18.711,-13.577]],"o":[[-11.303,-7.177],[0,0]],"v":[[19.675,15.44],[-30.744,15.498]],"c":false}]},{"i":{"x":0.667,"y":1},"o":{"x":0.333,"y":0},"n":"0p667_1_0p333_0","t":32,"s":[{"i":[[0,0],[18.711,-13.577]],"o":[[-11.303,-7.177],[0,0]],"v":[[19.675,15.44],[-30.744,15.498]],"c":false}],"e":[{"i":[[0,0],[25.345,-0.643]],"o":[[-7.667,-1.094],[0,0]],"v":[[19.675,15.44],[-27.011,-6.767]],"c":false}]},{"i":{"x":0.667,"y":1},"o":{"x":0.333,"y":0},"n":"0p667_1_0p333_0","t":36,"s":[{"i":[[0,0],[25.345,-0.643]],"o":[[-7.667,-1.094],[0,0]],"v":[[19.675,15.44],[-27.011,-6.767]],"c":false}],"e":[{"i":[[0,0],[10.379,15.746]],"o":[[-13.394,0.224],[0,0]],"v":[[19.675,15.44],[-21.986,-18.786]],"c":false}]},{"i":{"x":0.667,"y":1},"o":{"x":0.333,"y":0},"n":"0p667_1_0p333_0","t":38,"s":[{"i":[[0,0],[10.379,15.746]],"o":[[-13.394,0.224],[0,0]],"v":[[19.675,15.44],[-21.986,-18.786]],"c":false}],"e":[{"i":[[0,0],[4.116,22.688]],"o":[[-19.121,1.542],[0,0]],"v":[[19.675,15.44],[-22.085,-16.512]],"c":false}]},{"i":{"x":0.334,"y":1},"o":{"x":0.333,"y":0},"n":"0p334_1_0p333_0","t":40,"s":[{"i":[[0,0],[4.116,22.688]],"o":[[-19.121,1.542],[0,0]],"v":[[19.675,15.44],[-22.085,-16.512]],"c":false}],"e":[{"i":[[0,0],[12.161,19.2]],"o":[[-4.596,-11.772],[0,0]],"v":[[19.675,15.44],[-30.198,1.176]],"c":false}]},{"t":51}],"ix":2},"nm":"Path 1","mn":"ADBE Vector Shape - Group","hd":false},{"ty":"st","c":{"a":0,"k":[0.960784313725,0.545098039216,0.278431372549,1],"ix":3},"o":{"a":0,"k":100,"ix":4},"w":{"a":0,"k":8.84,"ix":5},"lc":2,"lj":2,"nm":"Stroke 1","mn":"ADBE Vector Graphic - Stroke","hd":false},{"ty":"tr","p":{"a":0,"k":[290.174,89.805],"ix":2},"a":{"a":0,"k":[0,0],"ix":1},"s":{"a":0,"k":[100,100],"ix":3},"r":{"a":0,"k":-0.147,"ix":6},"o":{"a":0,"k":100,"ix":7},"sk":{"a":0,"k":0,"ix":4},"sa":{"a":0,"k":0,"ix":5},"nm":"Transform"}],"nm":"Group 18","np":2,"cix":2,"ix":1,"mn":"ADBE Vector Group","hd":false}],"ip":0,"op":240,"st":0,"bm":0},{"ddd":0,"ind":7,"ty":4,"nm":"tiger 1 head","parent":1,"sr":1,"ks":{"o":{"a":0,"k":100,"ix":11},"r":{"a":1,"k":[{"i":{"x":[0.338],"y":[1]},"o":{"x":[0.84],"y":[0]},"n":["0p338_1_0p84_0"],"t":19,"s":[0],"e":[-22]},{"i":{"x":[0.667],"y":[1]},"o":{"x":[0.333],"y":[0]},"n":["0p667_1_0p333_0"],"t":31,"s":[-22],"e":[-22]},{"i":{"x":[0.351],"y":[1]},"o":{"x":[0.808],"y":[0]},"n":["0p351_1_0p808_0"],"t":48,"s":[-22],"e":[0]},{"t":60}],"ix":10},"p":{"a":0,"k":[42.426,-68.486,0],"ix":2},"a":{"a":0,"k":[71.507,44.618,0],"ix":1},"s":{"a":0,"k":[100,100,100],"ix":6}},"ao":0,"shapes":[{"ty":"gr","it":[{"ty":"rc","d":1,"s":{"a":1,"k":[{"i":{"x":[0.667,0.667],"y":[1,1]},"o":{"x":[0.333,0.333],"y":[0,0]},"n":["0p667_1_0p333_0","0p667_1_0p333_0"],"t":13,"s":[27,27],"e":[27,8]},{"i":{"x":[0.667,0.667],"y":[1,1]},"o":{"x":[0.333,0.333],"y":[0,0]},"n":["0p667_1_0p333_0","0p667_1_0p333_0"],"t":14,"s":[27,8],"e":[27,27]},{"i":{"x":[0.667,0.667],"y":[1,1]},"o":{"x":[0.333,0.333],"y":[0,0]},"n":["0p667_1_0p333_0","0p667_1_0p333_0"],"t":17,"s":[27,27],"e":[27,27]},{"i":{"x":[0.667,0.667],"y":[1,1]},"o":{"x":[0.333,0.333],"y":[0,0]},"n":["0p667_1_0p333_0","0p667_1_0p333_0"],"t":33,"s":[27,27],"e":[27,8]},{"i":{"x":[0.667,0.667],"y":[1,1]},"o":{"x":[0.333,0.333],"y":[0,0]},"n":["0p667_1_0p333_0","0p667_1_0p333_0"],"t":34,"s":[27,8],"e":[27,27]},{"t":37}],"ix":2},"p":{"a":0,"k":[0,0],"ix":3},"r":{"a":0,"k":38,"ix":4},"nm":"Rectangle Path 1","mn":"ADBE Vector Shape - Rect","hd":false},{"ty":"fl","c":{"a":0,"k":[0.301960784314,0.262745098039,0.372549019608,1],"ix":4},"o":{"a":0,"k":100,"ix":5},"r":1,"nm":"Fill 1","mn":"ADBE Vector Graphic - Fill","hd":false},{"ty":"tr","p":{"a":0,"k":[83.121,35.002],"ix":2},"a":{"a":0,"k":[0,0],"ix":1},"s":{"a":0,"k":[38.07,38.07],"ix":3},"r":{"a":0,"k":0,"ix":6},"o":{"a":0,"k":100,"ix":7},"sk":{"a":0,"k":0,"ix":4},"sa":{"a":0,"k":0,"ix":5},"nm":"Transform"}],"nm":"eye 2","np":2,"cix":2,"ix":1,"mn":"ADBE Vector Group","hd":false},{"ty":"gr","it":[{"ty":"rc","d":1,"s":{"a":1,"k":[{"i":{"x":[0.667,0.667],"y":[1,1]},"o":{"x":[0.333,0.333],"y":[0,0]},"n":["0p667_1_0p333_0","0p667_1_0p333_0"],"t":13,"s":[27,27],"e":[27,8]},{"i":{"x":[0.667,0.667],"y":[1,1]},"o":{"x":[0.333,0.333],"y":[0,0]},"n":["0p667_1_0p333_0","0p667_1_0p333_0"],"t":14,"s":[27,8],"e":[27,27]},{"i":{"x":[0.667,0.667],"y":[1,1]},"o":{"x":[0.333,0.333],"y":[0,0]},"n":["0p667_1_0p333_0","0p667_1_0p333_0"],"t":17,"s":[27,27],"e":[27,27]},{"i":{"x":[0.667,0.667],"y":[1,1]},"o":{"x":[0.333,0.333],"y":[0,0]},"n":["0p667_1_0p333_0","0p667_1_0p333_0"],"t":33,"s":[27,27],"e":[27,8]},{"i":{"x":[0.667,0.667],"y":[1,1]},"o":{"x":[0.333,0.333],"y":[0,0]},"n":["0p667_1_0p333_0","0p667_1_0p333_0"],"t":34,"s":[27,8],"e":[27,27]},{"t":37}],"ix":2},"p":{"a":0,"k":[0,0],"ix":3},"r":{"a":0,"k":38,"ix":4},"nm":"Rectangle Path 1","mn":"ADBE Vector Shape - Rect","hd":false},{"ty":"fl","c":{"a":0,"k":[0.301960784314,0.262745098039,0.372549019608,1],"ix":4},"o":{"a":0,"k":100,"ix":5},"r":1,"nm":"Fill 1","mn":"ADBE Vector Graphic - Fill","hd":false},{"ty":"tr","p":{"a":0,"k":[60.621,35.002],"ix":2},"a":{"a":0,"k":[0,0],"ix":1},"s":{"a":0,"k":[38.07,38.07],"ix":3},"r":{"a":0,"k":0,"ix":6},"o":{"a":0,"k":100,"ix":7},"sk":{"a":0,"k":0,"ix":4},"sa":{"a":0,"k":0,"ix":5},"nm":"Transform"}],"nm":"eye 1","np":2,"cix":2,"ix":2,"mn":"ADBE Vector Group","hd":false},{"ty":"gr","it":[{"ind":0,"ty":"sh","ix":1,"ks":{"a":0,"k":{"i":[[0,0],[-1.937,-1.941],[-2.492,1.33]],"o":[[2.493,1.33],[1.935,-1.939],[0,0]],"v":[[-6.737,-2.462],[0.002,2.462],[6.737,-2.458]],"c":false},"ix":2},"nm":"Path 1","mn":"ADBE Vector Shape - Group","hd":false},{"ty":"st","c":{"a":0,"k":[0.301999978458,0.263000009574,0.372999991623,1],"ix":3},"o":{"a":0,"k":100,"ix":4},"w":{"a":0,"k":4.421,"ix":5},"lc":2,"lj":2,"nm":"Stroke 1","mn":"ADBE Vector Graphic - Stroke","hd":false},{"ty":"tr","p":{"a":0,"k":[71.856,13.514],"ix":2},"a":{"a":0,"k":[0,0],"ix":1},"s":{"a":0,"k":[100,100],"ix":3},"r":{"a":0,"k":0,"ix":6},"o":{"a":0,"k":100,"ix":7},"sk":{"a":0,"k":0,"ix":4},"sa":{"a":0,"k":0,"ix":5},"nm":"Transform"}],"nm":"Group 10","np":2,"cix":2,"ix":3,"mn":"ADBE Vector Group","hd":false},{"ty":"gr","it":[{"ind":0,"ty":"sh","ix":1,"ks":{"a":0,"k":{"i":[[0,0],[-3.92,-3.929],[-5.399,1.282]],"o":[[5.4,1.282],[3.92,-3.929],[0,0]],"v":[[-14.771,-3.979],[0,3.979],[14.771,-3.979]],"c":false},"ix":2},"nm":"Path 1","mn":"ADBE Vector Shape - Group","hd":false},{"ty":"st","c":{"a":0,"k":[0.301999978458,0.263000009574,0.372999991623,1],"ix":3},"o":{"a":0,"k":100,"ix":4},"w":{"a":0,"k":4.421,"ix":5},"lc":2,"lj":2,"nm":"Stroke 1","mn":"ADBE Vector Graphic - Stroke","hd":false},{"ty":"tr","p":{"a":0,"k":[71.858,22.615],"ix":2},"a":{"a":0,"k":[0,0],"ix":1},"s":{"a":0,"k":[100,100],"ix":3},"r":{"a":0,"k":0,"ix":6},"o":{"a":0,"k":100,"ix":7},"sk":{"a":0,"k":0,"ix":4},"sa":{"a":0,"k":0,"ix":5},"nm":"Transform"}],"nm":"Group 11","np":2,"cix":2,"ix":4,"mn":"ADBE Vector Group","hd":false},{"ty":"gr","it":[{"ind":0,"ty":"sh","ix":1,"ks":{"a":0,"k":{"i":[[0,0],[0,0],[0,0],[0,0],[0,0],[0,0]],"o":[[0,0],[0,0],[0,0],[0,0],[0,0],[0,0]],"v":[[0,-2.142],[0,-0.759],[4.199,2.142],[0,1.454],[-4.199,2.142],[0,-0.759]],"c":false},"ix":2},"nm":"Path 1","mn":"ADBE Vector Shape - Group","hd":false},{"ty":"st","c":{"a":0,"k":[0.301999978458,0.263000009574,0.372999991623,1],"ix":3},"o":{"a":0,"k":100,"ix":4},"w":{"a":0,"k":3.536,"ix":5},"lc":2,"lj":2,"nm":"Stroke 1","mn":"ADBE Vector Graphic - Stroke","hd":false},{"ty":"tr","p":{"a":0,"k":[71.858,56.193],"ix":2},"a":{"a":0,"k":[0,0],"ix":1},"s":{"a":0,"k":[100,100],"ix":3},"r":{"a":0,"k":0,"ix":6},"o":{"a":0,"k":100,"ix":7},"sk":{"a":0,"k":0,"ix":4},"sa":{"a":0,"k":0,"ix":5},"nm":"Transform"}],"nm":"Group 12","np":2,"cix":2,"ix":5,"mn":"ADBE Vector Group","hd":false},{"ty":"gr","it":[{"ind":0,"ty":"sh","ix":1,"ks":{"a":0,"k":{"i":[[0,0],[0,0],[0,0],[0,0],[0,0],[0,0]],"o":[[0,0],[0,0],[0,0],[0,0],[0,0],[0,0]],"v":[[0,-2.142],[0,-0.759],[4.199,2.142],[0,1.454],[-4.199,2.142],[0,-0.759]],"c":false},"ix":2},"nm":"Path 1","mn":"ADBE Vector Shape - Group","hd":false},{"ty":"fl","c":{"a":0,"k":[0.301999978458,0.263000009574,0.372999991623,1],"ix":4},"o":{"a":0,"k":100,"ix":5},"r":1,"nm":"Fill 1","mn":"ADBE Vector Graphic - Fill","hd":false},{"ty":"tr","p":{"a":0,"k":[71.858,56.193],"ix":2},"a":{"a":0,"k":[0,0],"ix":1},"s":{"a":0,"k":[100,100],"ix":3},"r":{"a":0,"k":0,"ix":6},"o":{"a":0,"k":100,"ix":7},"sk":{"a":0,"k":0,"ix":4},"sa":{"a":0,"k":0,"ix":5},"nm":"Transform"}],"nm":"Group 13","np":2,"cix":2,"ix":6,"mn":"ADBE Vector Group","hd":false},{"ty":"gr","it":[{"ind":0,"ty":"sh","ix":1,"ks":{"a":0,"k":{"i":[[0,0],[0,0],[0,0],[0,0],[0,0],[0,0]],"o":[[0,0],[0,0],[0,0],[0,0],[0,0],[0,0]],"v":[[0,4.284],[0,1.517],[8.399,-4.284],[0,-2.907],[-8.399,-4.284],[0,1.517]],"c":false},"ix":2},"nm":"Path 1","mn":"ADBE Vector Shape - Group","hd":false},{"ty":"fl","c":{"a":0,"k":[0.301999978458,0.263000009574,0.372999991623,1],"ix":4},"o":{"a":0,"k":100,"ix":5},"r":1,"nm":"Fill 1","mn":"ADBE Vector Graphic - Fill","hd":false},{"ty":"st","c":{"a":0,"k":[0.301999978458,0.263000009574,0.372999991623,1],"ix":3},"o":{"a":0,"k":100,"ix":4},"w":{"a":0,"k":3.536,"ix":5},"lc":2,"lj":2,"nm":"Stroke 1","mn":"ADBE Vector Graphic - Stroke","hd":false},{"ty":"tr","p":{"a":0,"k":[71.858,52.506],"ix":2},"a":{"a":0,"k":[0,0],"ix":1},"s":{"a":0,"k":[100,100],"ix":3},"r":{"a":0,"k":0,"ix":6},"o":{"a":0,"k":100,"ix":7},"sk":{"a":0,"k":0,"ix":4},"sa":{"a":0,"k":0,"ix":5},"nm":"Transform"}],"nm":"Group 15","np":3,"cix":2,"ix":7,"mn":"ADBE Vector Group","hd":false},{"ty":"gr","it":[{"ind":0,"ty":"sh","ix":1,"ks":{"a":0,"k":{"i":[[10.444,0],[5.028,8.336],[-3.241,5.47],[-4.179,-2.373],[0.766,-2.576],[-0.917,-1.949],[-1.339,-0.807],[-0.233,-0.39],[-0.044,-0.257],[-0.133,0.223],[-0.389,0.234],[0,0],[0.714,2.4],[-3.21,1.823],[-4.215,-7.113],[1.172,-6.547]],"o":[[-10.444,0],[-1.172,-6.547],[4.215,-7.113],[3.211,1.823],[-0.714,2.4],[0,0],[0.389,0.234],[0.134,0.223],[0.044,-0.257],[0.233,-0.39],[1.339,-0.807],[0.918,-1.949],[-0.766,-2.576],[4.18,-2.373],[3.241,5.47],[-5.028,8.336]],"v":[[0,21.818],[-24.612,7.908],[-21.75,-11.275],[-5.01,-19.445],[-4.719,-9.035],[-8.457,4.135],[-1.268,9.397],[-0.242,10.271],[0,11.005],[0.242,10.271],[1.268,9.397],[8.457,4.135],[4.72,-9.035],[5.01,-19.445],[21.75,-11.275],[24.612,7.908]],"c":true},"ix":2},"nm":"Path 1","mn":"ADBE Vector Shape - Group","hd":false},{"ty":"fl","c":{"a":0,"k":[0.925,0.902000038297,0.8,1],"ix":4},"o":{"a":0,"k":100,"ix":5},"r":1,"nm":"Fill 1","mn":"ADBE Vector Graphic - Fill","hd":false},{"ty":"tr","p":{"a":0,"k":[71.858,44.116],"ix":2},"a":{"a":0,"k":[0,0],"ix":1},"s":{"a":0,"k":[100,100],"ix":3},"r":{"a":0,"k":0,"ix":6},"o":{"a":0,"k":100,"ix":7},"sk":{"a":0,"k":0,"ix":4},"sa":{"a":0,"k":0,"ix":5},"nm":"Transform"}],"nm":"Group 18","np":2,"cix":2,"ix":8,"mn":"ADBE Vector Group","hd":false},{"ty":"gr","it":[{"ind":0,"ty":"sh","ix":1,"ks":{"a":0,"k":{"i":[[0,15.863],[-15.863,0],[0,-15.864],[15.864,0]],"o":[[0,-15.864],[15.864,0],[0,15.863],[-15.863,0]],"v":[[-28.723,0],[-0.001,-28.723],[28.723,0],[-0.001,28.723]],"c":true},"ix":2},"nm":"Path 1","mn":"ADBE Vector Shape - Group","hd":false},{"ty":"fl","c":{"a":0,"k":[0.961000031116,0.545000023935,0.277999997606,1],"ix":4},"o":{"a":0,"k":100,"ix":5},"r":1,"nm":"Fill 1","mn":"ADBE Vector Graphic - Fill","hd":false},{"ty":"tr","p":{"a":0,"k":[71.858,37.211],"ix":2},"a":{"a":0,"k":[0,0],"ix":1},"s":{"a":0,"k":[100,100],"ix":3},"r":{"a":0,"k":0,"ix":6},"o":{"a":0,"k":100,"ix":7},"sk":{"a":0,"k":0,"ix":4},"sa":{"a":0,"k":0,"ix":5},"nm":"Transform"}],"nm":"Group 19","np":2,"cix":2,"ix":9,"mn":"ADBE Vector Group","hd":false}],"ip":0,"op":240,"st":0,"bm":0},{"ddd":0,"ind":8,"ty":4,"nm":"tiger 1 ear 1","parent":7,"sr":1,"ks":{"o":{"a":0,"k":100,"ix":11},"r":{"a":1,"k":[{"i":{"x":[0.833],"y":[0.833]},"o":{"x":[0.167],"y":[0.167]},"n":["0p833_0p833_0p167_0p167"],"t":24,"s":[0],"e":[-21]},{"i":{"x":[0.833],"y":[0.833]},"o":{"x":[0.167],"y":[0.167]},"n":["0p833_0p833_0p167_0p167"],"t":26,"s":[-21],"e":[25]},{"i":{"x":[0.833],"y":[0.833]},"o":{"x":[0.167],"y":[0.167]},"n":["0p833_0p833_0p167_0p167"],"t":28,"s":[25],"e":[-13]},{"i":{"x":[0.833],"y":[0.833]},"o":{"x":[0.167],"y":[0.167]},"n":["0p833_0p833_0p167_0p167"],"t":30,"s":[-13],"e":[0]},{"t":32}],"ix":10},"p":{"a":0,"k":[53.507,20.118,0],"ix":2},"a":{"a":0,"k":[53.507,20.118,0],"ix":1},"s":{"a":0,"k":[100,100,100],"ix":6}},"ao":0,"shapes":[{"ty":"gr","it":[{"ind":0,"ty":"sh","ix":1,"ks":{"a":0,"k":{"i":[[0.18,-0.051],[0.086,-0.34],[0.199,-1.643],[-0.033,-0.067],[-3.416,-0.718],[0,0],[4.075,1.585]],"o":[[-0.313,0.088],[-0.402,1.598],[0.031,0.067],[1.551,3.126],[0,0],[-3.5,-2.77],[-0.174,-0.067]],"v":[[-5.286,-6.019],[-5.823,-5.199],[-6.691,-0.328],[-6.604,-0.124],[1.397,6.07],[6.691,0.649],[-4.744,-5.934]],"c":true},"ix":2},"nm":"Path 1","mn":"ADBE Vector Shape - Group","hd":false},{"ty":"fl","c":{"a":0,"k":[0.301999978458,0.263000009574,0.372999991623,1],"ix":4},"o":{"a":0,"k":100,"ix":5},"r":1,"nm":"Fill 1","mn":"ADBE Vector Graphic - Fill","hd":false},{"ty":"tr","p":{"a":0,"k":[49.323,17.055],"ix":2},"a":{"a":0,"k":[0,0],"ix":1},"s":{"a":0,"k":[100,100],"ix":3},"r":{"a":0,"k":0,"ix":6},"o":{"a":0,"k":100,"ix":7},"sk":{"a":0,"k":0,"ix":4},"sa":{"a":0,"k":0,"ix":5},"nm":"Transform"}],"nm":"Group 26","np":2,"cix":2,"ix":1,"mn":"ADBE Vector Group","hd":false},{"ty":"gr","it":[{"ind":0,"ty":"sh","ix":1,"ks":{"a":0,"k":{"i":[[0,0],[2.244,1.58],[2.637,0.759],[0.755,-0.57],[0.189,-0.399],[-1.551,-3.127],[-3.415,-0.718]],"o":[[-0.407,-2.714],[-2.244,-1.58],[-0.909,-0.261],[-0.352,0.265],[-1.494,3.154],[1.551,3.127],[0,0]],"v":[[8.494,1.396],[4.017,-5.246],[-3.507,-8.491],[-6.236,-8.403],[-7,-7.338],[-6.909,2.78],[1.093,8.973]],"c":false},"ix":2},"nm":"Path 1","mn":"ADBE Vector Shape - Group","hd":false},{"ty":"fl","c":{"a":0,"k":[0.961000031116,0.545000023935,0.277999997606,1],"ix":4},"o":{"a":0,"k":100,"ix":5},"r":1,"nm":"Fill 1","mn":"ADBE Vector Graphic - Fill","hd":false},{"ty":"tr","p":{"a":0,"k":[49.627,14.151],"ix":2},"a":{"a":0,"k":[0,0],"ix":1},"s":{"a":0,"k":[100,100],"ix":3},"r":{"a":0,"k":0,"ix":6},"o":{"a":0,"k":100,"ix":7},"sk":{"a":0,"k":0,"ix":4},"sa":{"a":0,"k":0,"ix":5},"nm":"Transform"}],"nm":"Group 27","np":2,"cix":2,"ix":2,"mn":"ADBE Vector Group","hd":false}],"ip":0,"op":240,"st":0,"bm":0},{"ddd":0,"ind":9,"ty":4,"nm":"tiger 1 ear 2","parent":7,"sr":1,"ks":{"o":{"a":0,"k":100,"ix":11},"r":{"a":1,"k":[{"i":{"x":[0.833],"y":[0.833]},"o":{"x":[0.167],"y":[0.167]},"n":["0p833_0p833_0p167_0p167"],"t":27,"s":[0],"e":[-26]},{"i":{"x":[0.833],"y":[0.833]},"o":{"x":[0.167],"y":[0.167]},"n":["0p833_0p833_0p167_0p167"],"t":29,"s":[-26],"e":[19]},{"i":{"x":[0.833],"y":[0.833]},"o":{"x":[0.167],"y":[0.167]},"n":["0p833_0p833_0p167_0p167"],"t":31,"s":[19],"e":[-10]},{"i":{"x":[0.833],"y":[0.833]},"o":{"x":[0.167],"y":[0.167]},"n":["0p833_0p833_0p167_0p167"],"t":33,"s":[-10],"e":[0]},{"t":36}],"ix":10},"p":{"a":0,"k":[89.507,20.118,0],"ix":2},"a":{"a":0,"k":[89.507,20.118,0],"ix":1},"s":{"a":0,"k":[100,100,100],"ix":6}},"ao":0,"shapes":[{"ty":"gr","it":[{"ind":0,"ty":"sh","ix":1,"ks":{"a":0,"k":{"i":[[-0.18,-0.051],[-0.086,-0.34],[-0.199,-1.643],[0.033,-0.067],[3.416,-0.718],[0,0],[-4.074,1.585]],"o":[[0.312,0.088],[0.402,1.598],[-0.031,0.067],[-1.551,3.126],[0,0],[3.5,-2.77],[0.175,-0.067]],"v":[[5.287,-6.019],[5.823,-5.199],[6.691,-0.328],[6.604,-0.124],[-1.397,6.07],[-6.691,0.649],[4.743,-5.934]],"c":true},"ix":2},"nm":"Path 1","mn":"ADBE Vector Shape - Group","hd":false},{"ty":"fl","c":{"a":0,"k":[0.301999978458,0.263000009574,0.372999991623,1],"ix":4},"o":{"a":0,"k":100,"ix":5},"r":1,"nm":"Fill 1","mn":"ADBE Vector Graphic - Fill","hd":false},{"ty":"tr","p":{"a":0,"k":[94.393,17.055],"ix":2},"a":{"a":0,"k":[0,0],"ix":1},"s":{"a":0,"k":[100,100],"ix":3},"r":{"a":0,"k":0,"ix":6},"o":{"a":0,"k":100,"ix":7},"sk":{"a":0,"k":0,"ix":4},"sa":{"a":0,"k":0,"ix":5},"nm":"Transform"}],"nm":"Group 24","np":2,"cix":2,"ix":1,"mn":"ADBE Vector Group","hd":false},{"ty":"gr","it":[{"ind":0,"ty":"sh","ix":1,"ks":{"a":0,"k":{"i":[[0,0],[-2.244,1.58],[-2.637,0.759],[-0.754,-0.57],[-0.189,-0.399],[1.552,-3.127],[3.415,-0.718]],"o":[[0.407,-2.714],[2.244,-1.58],[0.909,-0.261],[0.353,0.265],[1.494,3.154],[-1.55,3.127],[0,0]],"v":[[-8.494,1.396],[-4.017,-5.246],[3.507,-8.491],[6.235,-8.403],[7,-7.338],[6.908,2.78],[-1.093,8.973]],"c":false},"ix":2},"nm":"Path 1","mn":"ADBE Vector Shape - Group","hd":false},{"ty":"fl","c":{"a":0,"k":[0.961000031116,0.545000023935,0.277999997606,1],"ix":4},"o":{"a":0,"k":100,"ix":5},"r":1,"nm":"Fill 1","mn":"ADBE Vector Graphic - Fill","hd":false},{"ty":"tr","p":{"a":0,"k":[94.089,14.151],"ix":2},"a":{"a":0,"k":[0,0],"ix":1},"s":{"a":0,"k":[100,100],"ix":3},"r":{"a":0,"k":0,"ix":6},"o":{"a":0,"k":100,"ix":7},"sk":{"a":0,"k":0,"ix":4},"sa":{"a":0,"k":0,"ix":5},"nm":"Transform"}],"nm":"Group 25","np":2,"cix":2,"ix":2,"mn":"ADBE Vector Group","hd":false}],"ip":0,"op":240,"st":0,"bm":0},{"ddd":0,"ind":10,"ty":4,"nm":"tiger 1","parent":1,"sr":1,"ks":{"o":{"a":0,"k":100,"ix":11},"r":{"a":0,"k":0,"ix":10},"p":{"a":0,"k":[103.426,-51.486,0],"ix":2},"a":{"a":0,"k":[132.507,61.618,0],"ix":1},"s":{"a":0,"k":[100,100,100],"ix":6}},"ao":0,"shapes":[{"ty":"gr","it":[{"ind":0,"ty":"sh","ix":1,"ks":{"a":0,"k":{"i":[[4.05,-4.669],[0.866,0],[0.585,0.507],[-1.12,1.292],[-0.291,6.951],[-0.828,0.525],[-0.868,-3.093]],"o":[[-0.611,0.706],[-0.719,0],[-1.292,-1.12],[4.369,-5.036],[0.044,-1.054],[1.8,2.548],[-1.229,6.194]],"v":[[-1.123,12.03],[-3.462,13.098],[-5.487,12.34],[-5.798,7.975],[1.428,-10.616],[2.879,-13.098],[6.918,-4.597]],"c":true},"ix":2},"nm":"Path 1","mn":"ADBE Vector Shape - Group","hd":false},{"ty":"fl","c":{"a":0,"k":[0.301999978458,0.263000009574,0.372999991623,1],"ix":4},"o":{"a":0,"k":100,"ix":5},"r":1,"nm":"Fill 1","mn":"ADBE Vector Graphic - Fill","hd":false},{"ty":"tr","p":{"a":0,"k":[191.755,52.549],"ix":2},"a":{"a":0,"k":[0,0],"ix":1},"s":{"a":0,"k":[100,100],"ix":3},"r":{"a":0,"k":0,"ix":6},"o":{"a":0,"k":100,"ix":7},"sk":{"a":0,"k":0,"ix":4},"sa":{"a":0,"k":0,"ix":5},"nm":"Transform"}],"nm":"Group 1","np":2,"cix":2,"ix":1,"mn":"ADBE Vector Group","hd":false},{"ty":"gr","it":[{"ind":0,"ty":"sh","ix":1,"ks":{"a":0,"k":{"i":[[1.244,0],[0.365,0.141],[-0.612,1.595],[0.063,5.915],[0.846,2.273],[-0.148,0.588],[-2.067,-0.955],[-0.026,-2.388],[1.96,-5.102]],"o":[[-0.369,0],[-1.594,-0.613],[1.873,-4.873],[-0.026,-2.589],[-0.226,-0.611],[2.382,0.487],[0.589,2.25],[0.073,6.997],[-0.474,1.23]],"v":[[-1.794,15.019],[-2.905,14.813],[-4.683,10.815],[-0.968,-5.752],[-2.301,-13.183],[-2.397,-15.019],[4.284,-12.841],[5.222,-5.818],[1.095,13.034]],"c":true},"ix":2},"nm":"Path 1","mn":"ADBE Vector Shape - Group","hd":false},{"ty":"fl","c":{"a":0,"k":[0.301999978458,0.263000009574,0.372999991623,1],"ix":4},"o":{"a":0,"k":100,"ix":5},"r":1,"nm":"Fill 1","mn":"ADBE Vector Graphic - Fill","hd":false},{"ty":"tr","p":{"a":0,"k":[179.411,43.241],"ix":2},"a":{"a":0,"k":[0,0],"ix":1},"s":{"a":0,"k":[100,100],"ix":3},"r":{"a":0,"k":0,"ix":6},"o":{"a":0,"k":100,"ix":7},"sk":{"a":0,"k":0,"ix":4},"sa":{"a":0,"k":0,"ix":5},"nm":"Transform"}],"nm":"Group 2","np":2,"cix":2,"ix":2,"mn":"ADBE Vector Group","hd":false},{"ty":"gr","it":[{"ind":0,"ty":"sh","ix":1,"ks":{"a":0,"k":{"i":[[0.493,1.191],[-0.785,5.091],[-0.124,1.419],[4.858,4.406],[0.148,0.553],[-2.349,0.286],[0.715,-8.181],[0.272,-1.754],[-1.397,-3.374],[1.578,-0.654],[0.396,0]],"o":[[-2.061,-4.974],[0.255,-1.651],[0.63,-7.2],[-0.456,-0.413],[2.292,-0.498],[4.954,5.413],[-0.141,1.622],[-0.693,4.498],[0.654,1.578],[-0.388,0.16],[-1.213,0]],"v":[[-0.125,19.128],[-0.51,3.292],[0.11,-1.337],[-6.088,-18.348],[-6.99,-19.833],[-0.037,-21.04],[6.275,-0.798],[5.606,4.237],[5.592,16.761],[3.918,20.804],[2.734,21.04]],"c":true},"ix":2},"nm":"Path 1","mn":"ADBE Vector Shape - Group","hd":false},{"ty":"fl","c":{"a":0,"k":[0.301999978458,0.263000009574,0.372999991623,1],"ix":4},"o":{"a":0,"k":100,"ix":5},"r":1,"nm":"Fill 1","mn":"ADBE Vector Graphic - Fill","hd":false},{"ty":"tr","p":{"a":0,"k":[162.617,48.989],"ix":2},"a":{"a":0,"k":[0,0],"ix":1},"s":{"a":0,"k":[100,100],"ix":3},"r":{"a":0,"k":0,"ix":6},"o":{"a":0,"k":100,"ix":7},"sk":{"a":0,"k":0,"ix":4},"sa":{"a":0,"k":0,"ix":5},"nm":"Transform"}],"nm":"Group 3","np":2,"cix":2,"ix":3,"mn":"ADBE Vector Group","hd":false},{"ty":"gr","it":[{"ind":0,"ty":"sh","ix":1,"ks":{"a":0,"k":{"i":[[1.549,0],[0.123,0.014],[-0.198,1.697],[5.298,3.558],[0.231,0.483],[-2.31,0.663],[0.86,-7.364]],"o":[[-0.119,0],[-1.697,-0.198],[0.714,-6.113],[-0.477,-0.32],[2.312,-0.668],[5.664,5.033],[-0.184,1.576]],"v":[[3.934,11.438],[3.571,11.417],[0.857,7.985],[-6.808,-8.183],[-7.864,-9.42],[-0.935,-11.438],[7.004,8.702]],"c":true},"ix":2},"nm":"Path 1","mn":"ADBE Vector Shape - Group","hd":false},{"ty":"fl","c":{"a":0,"k":[0.301999978458,0.263000009574,0.372999991623,1],"ix":4},"o":{"a":0,"k":100,"ix":5},"r":1,"nm":"Fill 1","mn":"ADBE Vector Graphic - Fill","hd":false},{"ty":"tr","p":{"a":0,"k":[147.238,42.995],"ix":2},"a":{"a":0,"k":[0,0],"ix":1},"s":{"a":0,"k":[100,100],"ix":3},"r":{"a":0,"k":0,"ix":6},"o":{"a":0,"k":100,"ix":7},"sk":{"a":0,"k":0,"ix":4},"sa":{"a":0,"k":0,"ix":5},"nm":"Transform"}],"nm":"Group 4","np":2,"cix":2,"ix":4,"mn":"ADBE Vector Group","hd":false},{"ty":"gr","it":[{"ind":0,"ty":"sh","ix":1,"ks":{"a":0,"k":{"i":[[1.439,0],[0.21,0.042],[-0.343,1.675],[4.13,4.498],[0.128,0.266],[-2.207,0.554],[1.41,-6.887]],"o":[[-0.206,0],[-1.674,-0.343],[1.187,-5.801],[-0.209,-0.228],[2.254,-0.399],[4.275,5.751],[-0.3,1.465]],"v":[[1.93,11.302],[1.305,11.24],[-1.105,7.587],[-5.875,-9.11],[-6.368,-9.86],[0.319,-11.302],[4.958,8.829]],"c":true},"ix":2},"nm":"Path 1","mn":"ADBE Vector Shape - Group","hd":false},{"ty":"fl","c":{"a":0,"k":[0.301999978458,0.263000009574,0.372999991623,1],"ix":4},"o":{"a":0,"k":100,"ix":5},"r":1,"nm":"Fill 1","mn":"ADBE Vector Graphic - Fill","hd":false},{"ty":"tr","p":{"a":0,"k":[132.505,46.657],"ix":2},"a":{"a":0,"k":[0,0],"ix":1},"s":{"a":0,"k":[100,100],"ix":3},"r":{"a":0,"k":0,"ix":6},"o":{"a":0,"k":100,"ix":7},"sk":{"a":0,"k":0,"ix":4},"sa":{"a":0,"k":0,"ix":5},"nm":"Transform"}],"nm":"Group 5","np":2,"cix":2,"ix":5,"mn":"ADBE Vector Group","hd":false},{"ty":"gr","it":[{"ind":0,"ty":"sh","ix":1,"ks":{"a":0,"k":{"i":[[1.609,0],[0.074,0.005],[-0.121,1.705],[0.727,4.023],[0.989,1.685],[0.03,0.466],[-2.187,0.188],[-0.423,-2.336],[0.323,-4.564]],"o":[[-0.074,0],[-1.704,-0.12],[0.295,-4.183],[-0.395,-2.186],[-0.252,-0.429],[2.163,-0.002],[0.958,1.968],[0.865,4.786],[-0.115,1.63]],"v":[[0.999,11.705],[0.777,11.698],[-2.091,8.392],[-2.217,-4.139],[-4.332,-10.056],[-4.738,-11.418],[1.784,-11.705],[3.873,-5.24],[4.082,8.829]],"c":true},"ix":2},"nm":"Path 1","mn":"ADBE Vector Shape - Group","hd":false},{"ty":"fl","c":{"a":0,"k":[0.301999978458,0.263000009574,0.372999991623,1],"ix":4},"o":{"a":0,"k":100,"ix":5},"r":1,"nm":"Fill 1","mn":"ADBE Vector Graphic - Fill","hd":false},{"ty":"tr","p":{"a":0,"k":[117.52,49.391],"ix":2},"a":{"a":0,"k":[0,0],"ix":1},"s":{"a":0,"k":[100,100],"ix":3},"r":{"a":0,"k":0,"ix":6},"o":{"a":0,"k":100,"ix":7},"sk":{"a":0,"k":0,"ix":4},"sa":{"a":0,"k":0,"ix":5},"nm":"Transform"}],"nm":"Group 6","np":2,"cix":2,"ix":6,"mn":"ADBE Vector Group","hd":false},{"ty":"gr","it":[{"ind":0,"ty":"sh","ix":1,"ks":{"a":0,"k":{"i":[[1.022,0],[0.515,0.328],[-0.918,1.442],[2.114,6.077],[-0.128,0.551],[-2.07,-0.147],[4.219,-6.624]],"o":[[-0.569,0],[-1.442,-0.918],[3.342,-5.248],[-0.199,-0.573],[2.094,0.294],[2.352,7.68],[-0.59,0.927]],"v":[[-2.185,12.416],[-3.845,11.931],[-4.793,7.659],[-2.802,-10.702],[-2.885,-12.416],[3.359,-11.74],[0.427,10.983]],"c":true},"ix":2},"nm":"Path 1","mn":"ADBE Vector Shape - Group","hd":false},{"ty":"fl","c":{"a":0,"k":[0.301999978458,0.263000009574,0.372999991623,1],"ix":4},"o":{"a":0,"k":100,"ix":5},"r":1,"nm":"Fill 1","mn":"ADBE Vector Graphic - Fill","hd":false},{"ty":"tr","p":{"a":0,"k":[103.599,49.526],"ix":2},"a":{"a":0,"k":[0,0],"ix":1},"s":{"a":0,"k":[100,100],"ix":3},"r":{"a":0,"k":0,"ix":6},"o":{"a":0,"k":100,"ix":7},"sk":{"a":0,"k":0,"ix":4},"sa":{"a":0,"k":0,"ix":5},"nm":"Transform"}],"nm":"Group 7","np":2,"cix":2,"ix":7,"mn":"ADBE Vector Group","hd":false},{"ty":"gr","it":[{"ind":0,"ty":"sh","ix":1,"ks":{"a":0,"k":{"i":[[0,0],[0,13.518]],"o":[[13.396,0],[0,0]],"v":[[-11.308,11.421],[11.308,-11.421]],"c":false},"ix":2},"nm":"Path 1","mn":"ADBE Vector Shape - Group","hd":false},{"ty":"st","c":{"a":0,"k":[0.961000031116,0.545000023935,0.277999997606,1],"ix":3},"o":{"a":0,"k":100,"ix":4},"w":{"a":0,"k":13.262,"ix":5},"lc":2,"lj":2,"nm":"Stroke 1","mn":"ADBE Vector Graphic - Stroke","hd":false},{"ty":"tr","p":{"a":0,"k":[105.199,73.656],"ix":2},"a":{"a":0,"k":[0,0],"ix":1},"s":{"a":0,"k":[100,100],"ix":3},"r":{"a":0,"k":0,"ix":6},"o":{"a":0,"k":100,"ix":7},"sk":{"a":0,"k":0,"ix":4},"sa":{"a":0,"k":0,"ix":5},"nm":"Transform"}],"nm":"Group 8","np":2,"cix":2,"ix":8,"mn":"ADBE Vector Group","hd":false},{"ty":"gr","it":[{"ind":0,"ty":"sh","ix":1,"ks":{"a":0,"k":{"i":[[0,0],[9.284,-3.101],[11.076,0.472],[9.512,-5.694]],"o":[[0.75,9.541],[-10.515,3.513],[-11.076,-0.471],[0,0]],"v":[[39.837,-16.031],[24.708,8.506],[-8.284,10.516],[-40.587,16.031]],"c":false},"ix":2},"nm":"Path 1","mn":"ADBE Vector Shape - Group","hd":false},{"ty":"st","c":{"a":0,"k":[0.961000031116,0.545000023935,0.277999997606,1],"ix":3},"o":{"a":0,"k":100,"ix":4},"w":{"a":0,"k":13.262,"ix":5},"lc":2,"lj":2,"nm":"Stroke 1","mn":"ADBE Vector Graphic - Stroke","hd":false},{"ty":"tr","p":{"a":0,"k":[87.899,74.051],"ix":2},"a":{"a":0,"k":[0,0],"ix":1},"s":{"a":0,"k":[100,100],"ix":3},"r":{"a":0,"k":0,"ix":6},"o":{"a":0,"k":100,"ix":7},"sk":{"a":0,"k":0,"ix":4},"sa":{"a":0,"k":0,"ix":5},"nm":"Transform"}],"nm":"Group 9","np":2,"cix":2,"ix":9,"mn":"ADBE Vector Group","hd":false},{"ty":"gr","it":[{"ind":0,"ty":"sh","ix":1,"ks":{"a":0,"k":{"i":[[0,0],[-2.578,-6.679],[-5.277,-4.837],[8.129,-0.295],[2.258,-5.751],[-0.241,-0.745],[-1.41,-0.289],[-18.865,0],[7.248,12.048]],"o":[[-6.074,3.788],[2.577,6.679],[-7.539,-3.057],[-6.175,0.223],[-0.287,0.73],[0.444,1.369],[10.605,2.173],[12.23,0],[0,0]],"v":[[-4.864,-23.11],[-9.629,-3.893],[3.676,12.707],[-20.18,8.501],[-35.741,16.465],[-35.979,18.757],[-32.496,20.937],[16.902,22.466],[28.972,-2.627]],"c":false},"ix":2},"nm":"Path 1","mn":"ADBE Vector Shape - Group","hd":false},{"ty":"fl","c":{"a":0,"k":[0.961000031116,0.545000023935,0.277999997606,1],"ix":4},"o":{"a":0,"k":100,"ix":5},"r":1,"nm":"Fill 1","mn":"ADBE Vector Graphic - Fill","hd":false},{"ty":"tr","p":{"a":0,"k":[163.556,74.071],"ix":2},"a":{"a":0,"k":[0,0],"ix":1},"s":{"a":0,"k":[100,100],"ix":3},"r":{"a":0,"k":0,"ix":6},"o":{"a":0,"k":100,"ix":7},"sk":{"a":0,"k":0,"ix":4},"sa":{"a":0,"k":0,"ix":5},"nm":"Transform"}],"nm":"Group 20","np":2,"cix":2,"ix":10,"mn":"ADBE Vector Group","hd":false},{"ty":"gr","it":[{"ind":0,"ty":"sh","ix":1,"ks":{"a":0,"k":{"i":[[-4.364,0],[-4.328,2.131],[-7.044,0.097],[-10.368,3.228],[-6.301,-19.195],[9.109,0],[0,0],[7.058,11.208]],"o":[[5.15,0],[7.027,2.911],[10.931,-0.15],[16.725,-5.207],[-6.804,5.013],[0,0],[-12.829,0],[3.803,1.559]],"v":[[-52.128,0.203],[-37.782,-3.128],[-15.469,0.783],[14.779,-8.647],[64.454,7.374],[39.526,13.854],[-31.26,13.854],[-64.454,-2.221]],"c":true},"ix":2},"nm":"Path 1","mn":"ADBE Vector Shape - Group","hd":false},{"ty":"fl","c":{"a":0,"k":[0.925,0.902000038297,0.8,1],"ix":4},"o":{"a":0,"k":100,"ix":5},"r":1,"nm":"Fill 1","mn":"ADBE Vector Graphic - Fill","hd":false},{"ty":"tr","p":{"a":0,"k":[123.986,73.345],"ix":2},"a":{"a":0,"k":[0,0],"ix":1},"s":{"a":0,"k":[100,100],"ix":3},"r":{"a":0,"k":0,"ix":6},"o":{"a":0,"k":100,"ix":7},"sk":{"a":0,"k":0,"ix":4},"sa":{"a":0,"k":0,"ix":5},"nm":"Transform"}],"nm":"Group 22","np":2,"cix":2,"ix":11,"mn":"ADBE Vector Group","hd":false},{"ty":"gr","it":[{"ind":0,"ty":"sh","ix":1,"ks":{"a":0,"k":{"i":[[-9.871,1.582],[-16.555,-0.689],[7.177,-20.474],[14.46,0],[0,0],[6.943,11.684],[-11.105,6.785],[-5.383,-0.364],[-5.304,-0.992]],"o":[[15.798,-2.532],[21.067,0.876],[-5.511,15.716],[0,0],[-13.081,0],[-6.02,-10.132],[4.605,-2.812],[5.383,0.365],[9.85,1.842]],"v":[[-4.041,-20.025],[42.596,-29.476],[68.725,10.758],[34.523,30.165],[-36.263,30.165],[-69.882,13.438],[-64.609,-20.253],[-48.993,-23.396],[-33.045,-20.694]],"c":true},"ix":2},"nm":"Path 1","mn":"ADBE Vector Shape - Group","hd":false},{"ty":"fl","c":{"a":0,"k":[0.961000031116,0.545000023935,0.277999997606,1],"ix":4},"o":{"a":0,"k":100,"ix":5},"r":1,"nm":"Fill 1","mn":"ADBE Vector Graphic - Fill","hd":false},{"ty":"tr","p":{"a":0,"k":[128.988,57.035],"ix":2},"a":{"a":0,"k":[0,0],"ix":1},"s":{"a":0,"k":[100,100],"ix":3},"r":{"a":0,"k":0,"ix":6},"o":{"a":0,"k":100,"ix":7},"sk":{"a":0,"k":0,"ix":4},"sa":{"a":0,"k":0,"ix":5},"nm":"Transform"}],"nm":"Group 23","np":2,"cix":2,"ix":12,"mn":"ADBE Vector Group","hd":false},{"ty":"gr","it":[{"ind":0,"ty":"sh","ix":1,"ks":{"a":0,"k":{"i":[[0,0],[5.139,-1.718],[11.075,0.471],[9.512,-5.693]],"o":[[-0.906,5.341],[-10.514,3.512],[-11.077,-0.471],[0,0]],"v":[[38.31,-9.022],[26.985,1.498],[-6.006,3.509],[-38.31,9.022]],"c":false},"ix":2},"nm":"Path 1","mn":"ADBE Vector Shape - Group","hd":false},{"ty":"st","c":{"a":0,"k":[0.961000031116,0.545000023935,0.277999997606,1],"ix":3},"o":{"a":0,"k":100,"ix":4},"w":{"a":0,"k":13.262,"ix":5},"lc":2,"lj":2,"nm":"Stroke 1","mn":"ADBE Vector Graphic - Stroke","hd":false},{"ty":"tr","p":{"a":0,"k":[71.464,72.211],"ix":2},"a":{"a":0,"k":[0,0],"ix":1},"s":{"a":0,"k":[100,100],"ix":3},"r":{"a":0,"k":0,"ix":6},"o":{"a":0,"k":100,"ix":7},"sk":{"a":0,"k":0,"ix":4},"sa":{"a":0,"k":0,"ix":5},"nm":"Transform"}],"nm":"Group 28","np":2,"cix":2,"ix":13,"mn":"ADBE Vector Group","hd":false}],"ip":0,"op":240,"st":0,"bm":0},{"ddd":0,"ind":11,"ty":4,"nm":"tiger tail 1","parent":10,"sr":1,"ks":{"o":{"a":0,"k":100,"ix":11},"r":{"a":1,"k":[{"i":{"x":[0.667],"y":[1]},"o":{"x":[0.333],"y":[0]},"n":["0p667_1_0p333_0"],"t":13,"s":[36],"e":[4]},{"i":{"x":[0.667],"y":[1]},"o":{"x":[0.333],"y":[0]},"n":["0p667_1_0p333_0"],"t":28,"s":[4],"e":[51]},{"i":{"x":[0.667],"y":[1]},"o":{"x":[0.333],"y":[0]},"n":["0p667_1_0p333_0"],"t":34,"s":[51],"e":[36]},{"i":{"x":[0.667],"y":[1]},"o":{"x":[0.333],"y":[0]},"n":["0p667_1_0p333_0"],"t":39,"s":[36],"e":[4]},{"i":{"x":[0.667],"y":[1]},"o":{"x":[0.333],"y":[0]},"n":["0p667_1_0p333_0"],"t":50,"s":[4],"e":[51]},{"i":{"x":[0.667],"y":[1]},"o":{"x":[0.333],"y":[0]},"n":["0p667_1_0p333_0"],"t":56,"s":[51],"e":[36]},{"t":64}],"ix":10},"p":{"a":0,"k":[192.345,45.905,0],"ix":2},"a":{"a":0,"k":[309.857,105.518,0],"ix":1},"s":{"a":0,"k":[-113.859,100,100],"ix":6}},"ao":0,"shapes":[{"ty":"gr","it":[{"ind":0,"ty":"sh","ix":1,"ks":{"a":1,"k":[{"i":{"x":0.667,"y":1},"o":{"x":0.664,"y":0},"n":"0p667_1_0p664_0","t":13,"s":[{"i":[[0,0],[12.161,19.2]],"o":[[-4.596,-11.772],[0,0]],"v":[[19.675,15.44],[-30.198,1.176]],"c":false}],"e":[{"i":[[0,0],[15.802,7.359]],"o":[[-14.057,-11.784],[0,0]],"v":[[19.675,15.44],[-32.215,18.672]],"c":false}]},{"i":{"x":0.667,"y":1},"o":{"x":0.333,"y":0},"n":"0p667_1_0p333_0","t":17,"s":[{"i":[[0,0],[15.802,7.359]],"o":[[-14.057,-11.784],[0,0]],"v":[[19.675,15.44],[-32.215,18.672]],"c":false}],"e":[{"i":[[0,0],[12.848,-11.721]],"o":[[-12.68,-9.481],[0,0]],"v":[[19.675,15.44],[-31.357,20.283]],"c":false}]},{"i":{"x":0.667,"y":1},"o":{"x":0.333,"y":0},"n":"0p667_1_0p333_0","t":21,"s":[{"i":[[0,0],[12.848,-11.721]],"o":[[-12.68,-9.481],[0,0]],"v":[[19.675,15.44],[-31.357,20.283]],"c":false}],"e":[{"i":[[0,0],[18.711,-13.577]],"o":[[-11.303,-7.177],[0,0]],"v":[[19.675,15.44],[-30.744,15.498]],"c":false}]},{"i":{"x":0.667,"y":1},"o":{"x":0.333,"y":0},"n":"0p667_1_0p333_0","t":23,"s":[{"i":[[0,0],[18.711,-13.577]],"o":[[-11.303,-7.177],[0,0]],"v":[[19.675,15.44],[-30.744,15.498]],"c":false}],"e":[{"i":[[0,0],[25.345,-0.643]],"o":[[-7.667,-1.094],[0,0]],"v":[[19.675,15.44],[-27.011,-6.767]],"c":false}]},{"i":{"x":0.667,"y":1},"o":{"x":0.333,"y":0},"n":"0p667_1_0p333_0","t":27,"s":[{"i":[[0,0],[25.345,-0.643]],"o":[[-7.667,-1.094],[0,0]],"v":[[19.675,15.44],[-27.011,-6.767]],"c":false}],"e":[{"i":[[0,0],[10.379,15.746]],"o":[[-13.394,0.224],[0,0]],"v":[[19.675,15.44],[-21.986,-18.786]],"c":false}]},{"i":{"x":0.667,"y":1},"o":{"x":0.333,"y":0},"n":"0p667_1_0p333_0","t":29,"s":[{"i":[[0,0],[10.379,15.746]],"o":[[-13.394,0.224],[0,0]],"v":[[19.675,15.44],[-21.986,-18.786]],"c":false}],"e":[{"i":[[0,0],[4.116,22.688]],"o":[[-19.121,1.542],[0,0]],"v":[[19.675,15.44],[-22.085,-16.512]],"c":false}]},{"i":{"x":0.667,"y":1},"o":{"x":0.333,"y":0},"n":"0p667_1_0p333_0","t":31,"s":[{"i":[[0,0],[4.116,22.688]],"o":[[-19.121,1.542],[0,0]],"v":[[19.675,15.44],[-22.085,-16.512]],"c":false}],"e":[{"i":[[0,0],[15.802,7.359]],"o":[[-14.057,-11.784],[0,0]],"v":[[19.675,15.44],[-32.215,18.672]],"c":false}]},{"i":{"x":0.667,"y":1},"o":{"x":0.333,"y":0},"n":"0p667_1_0p333_0","t":39,"s":[{"i":[[0,0],[15.802,7.359]],"o":[[-14.057,-11.784],[0,0]],"v":[[19.675,15.44],[-32.215,18.672]],"c":false}],"e":[{"i":[[0,0],[12.848,-11.721]],"o":[[-12.68,-9.481],[0,0]],"v":[[19.675,15.44],[-31.357,20.283]],"c":false}]},{"i":{"x":0.667,"y":1},"o":{"x":0.333,"y":0},"n":"0p667_1_0p333_0","t":43,"s":[{"i":[[0,0],[12.848,-11.721]],"o":[[-12.68,-9.481],[0,0]],"v":[[19.675,15.44],[-31.357,20.283]],"c":false}],"e":[{"i":[[0,0],[18.711,-13.577]],"o":[[-11.303,-7.177],[0,0]],"v":[[19.675,15.44],[-30.744,15.498]],"c":false}]},{"i":{"x":0.667,"y":1},"o":{"x":0.333,"y":0},"n":"0p667_1_0p333_0","t":45,"s":[{"i":[[0,0],[18.711,-13.577]],"o":[[-11.303,-7.177],[0,0]],"v":[[19.675,15.44],[-30.744,15.498]],"c":false}],"e":[{"i":[[0,0],[25.345,-0.643]],"o":[[-7.667,-1.094],[0,0]],"v":[[19.675,15.44],[-27.011,-6.767]],"c":false}]},{"i":{"x":0.667,"y":1},"o":{"x":0.333,"y":0},"n":"0p667_1_0p333_0","t":49,"s":[{"i":[[0,0],[25.345,-0.643]],"o":[[-7.667,-1.094],[0,0]],"v":[[19.675,15.44],[-27.011,-6.767]],"c":false}],"e":[{"i":[[0,0],[10.379,15.746]],"o":[[-13.394,0.224],[0,0]],"v":[[19.675,15.44],[-21.986,-18.786]],"c":false}]},{"i":{"x":0.667,"y":1},"o":{"x":0.333,"y":0},"n":"0p667_1_0p333_0","t":51,"s":[{"i":[[0,0],[10.379,15.746]],"o":[[-13.394,0.224],[0,0]],"v":[[19.675,15.44],[-21.986,-18.786]],"c":false}],"e":[{"i":[[0,0],[4.116,22.688]],"o":[[-19.121,1.542],[0,0]],"v":[[19.675,15.44],[-22.085,-16.512]],"c":false}]},{"i":{"x":0.334,"y":1},"o":{"x":0.333,"y":0},"n":"0p334_1_0p333_0","t":53,"s":[{"i":[[0,0],[4.116,22.688]],"o":[[-19.121,1.542],[0,0]],"v":[[19.675,15.44],[-22.085,-16.512]],"c":false}],"e":[{"i":[[0,0],[12.161,19.2]],"o":[[-4.596,-11.772],[0,0]],"v":[[19.675,15.44],[-30.198,1.176]],"c":false}]},{"t":64}],"ix":2},"nm":"Path 1","mn":"ADBE Vector Shape - Group","hd":false},{"ty":"st","c":{"a":0,"k":[0.960784313725,0.545098039216,0.278431372549,1],"ix":3},"o":{"a":0,"k":100,"ix":4},"w":{"a":0,"k":8.84,"ix":5},"lc":2,"lj":2,"nm":"Stroke 1","mn":"ADBE Vector Graphic - Stroke","hd":false},{"ty":"tr","p":{"a":0,"k":[290.174,89.805],"ix":2},"a":{"a":0,"k":[0,0],"ix":1},"s":{"a":0,"k":[100,100],"ix":3},"r":{"a":0,"k":-0.147,"ix":6},"o":{"a":0,"k":100,"ix":7},"sk":{"a":0,"k":0,"ix":4},"sa":{"a":0,"k":0,"ix":5},"nm":"Transform"}],"nm":"Group 18","np":2,"cix":2,"ix":1,"mn":"ADBE Vector Group","hd":false}],"ip":0,"op":240,"st":0,"bm":0}]}